{"version":"0.4","title":"Zakra Business &#8211; Testimonials Section","type":"section","content":[{"id":"722cb3b6","settings":{"stretch_section":"section-stretched","background_background":"classic","background_color":"#f7f9fc","padding":{"unit":"px","top":"80","right":"0","bottom":"80","left":"0","isLinked":false},"gap":"no"},"elements":[{"id":"6b977134","settings":{"_column_size":100,"_inline_size":null,"margin_mobile":{"unit":"px","top":"0","right":"10","bottom":"0","left":"0","isLinked":false}},"elements":[{"id":"caf09fb","settings":{"title":"SAYING","size":"large","title_color":"#16181a","_margin_mobile":{"unit":"px","top":"0","right":"0","bottom":"0","left":"0","isLinked":true},"_padding_mobile":{"unit":"px","top":"0","right":"10","bottom":"0","left":"10","isLinked":false}},"elements":[],"isInner":false,"widgetType":"heading","elType":"widget"},{"id":"21a526","settings":{"editor":"<p>Know what people are saying about us and our services<\/p>","align":"left","_padding_mobile":{"unit":"px","top":"0","right":"10","bottom":"0","left":"10","isLinked":false}},"elements":[],"isInner":false,"widgetType":"text-editor","elType":"widget"},{"id":"284fdab4","settings":{"gap":"no","structure":"30","margin":{"unit":"px","top":"50","right":0,"bottom":"0","left":0,"isLinked":false}},"elements":[{"id":"62c18da9","settings":{"_column_size":33,"_inline_size":null,"background_background":"classic","background_color":"#ffffff","margin":{"unit":"px","top":"0","right":"20","bottom":"0","left":"0","isLinked":false},"padding":{"unit":"px","top":"40","right":"40","bottom":"40","left":"40","isLinked":true},"margin_mobile":{"unit":"px","top":"0","right":"10","bottom":"30","left":"10","isLinked":false}},"elements":[{"id":"73ee0df5","settings":{"image":{"url":"https:\/\/zakrademos.com\/business\/wp-content\/uploads\/sites\/2\/2018\/08\/28m.jpg","id":33},"image_size":"full","align":"center"},"elements":[],"isInner":false,"widgetType":"image","elType":"widget"},{"id":"32e54a89","settings":{"editor":"<p>They are the best company that will give you best product in such a price you will even doubt even if it\u2019s real<\/p>","align":"center"},"elements":[],"isInner":false,"widgetType":"text-editor","elType":"widget"},{"id":"27693c08","settings":{"title":"John Morgovic","header_size":"h4","title_color":"#16181a","size":"medium","align":"center"},"elements":[],"isInner":false,"widgetType":"heading","elType":"widget"},{"id":"6f967545","settings":{"editor":"<p>Co-founder &amp; CEO<\/p>","text_color":"#4286f5","typography_typography":"custom","align":"center"},"elements":[],"isInner":false,"widgetType":"text-editor","elType":"widget"}],"isInner":true,"elType":"column"},{"id":"6934d3ea","settings":{"_column_size":33,"_inline_size":null,"background_background":"classic","background_color":"#ffffff","margin":{"unit":"px","top":"0","right":"10","bottom":"0","left":"10","isLinked":false},"padding":{"unit":"px","top":"40","right":"40","bottom":"40","left":"40","isLinked":true},"margin_mobile":{"unit":"px","top":"0","right":"10","bottom":"30","left":"10","isLinked":false}},"elements":[{"id":"55f5f327","settings":{"image":{"url":"https:\/\/zakrademos.com\/business\/wp-content\/uploads\/sites\/2\/2018\/08\/13m.jpg","id":35},"image_size":"full","align":"center"},"elements":[],"isInner":false,"widgetType":"image","elType":"widget"},{"id":"216b9930","settings":{"editor":"<p>They are the best company that will give you best product in such a price you will even doubt even if it\u2019s real<\/p>","align":"center"},"elements":[],"isInner":false,"widgetType":"text-editor","elType":"widget"},{"id":"22d416f","settings":{"title":"Mathew Adams","header_size":"h4","title_color":"#16181a","size":"medium","align":"center"},"elements":[],"isInner":false,"widgetType":"heading","elType":"widget"},{"id":"82989a8","settings":{"editor":"<p>Manager<\/p>","text_color":"#4286f5","align":"center"},"elements":[],"isInner":false,"widgetType":"text-editor","elType":"widget"}],"isInner":true,"elType":"column"},{"id":"50e5b6b8","settings":{"_column_size":33,"_inline_size":null,"background_background":"classic","background_color":"#ffffff","margin":{"unit":"px","top":"0","right":"0","bottom":"0","left":"20","isLinked":false},"padding":{"unit":"px","top":"40","right":"40","bottom":"40","left":"40","isLinked":true},"margin_mobile":{"unit":"px","top":"0","right":"10","bottom":"0","left":"10","isLinked":false}},"elements":[{"id":"1bbc98c0","settings":{"image":{"url":"https:\/\/zakrademos.com\/business\/wp-content\/uploads\/sites\/2\/2018\/08\/02m.jpg","id":34},"image_size":"full","align":"center"},"elements":[],"isInner":false,"widgetType":"image","elType":"widget"},{"id":"71cf4cdb","settings":{"editor":"<p>They are the best company that will give you best product in such a price you will even doubt even if it\u2019s real<\/p>","align":"center"},"elements":[],"isInner":false,"widgetType":"text-editor","elType":"widget"},{"id":"3b2f054a","settings":{"title":"Josh Swaz","header_size":"h4","title_color":"#16181a","size":"medium","align":"center"},"elements":[],"isInner":false,"widgetType":"heading","elType":"widget"},{"id":"690a80a","settings":{"editor":"<p>Officer<\/p>","text_color":"#4286f5","align":"center"},"elements":[],"isInner":false,"widgetType":"text-editor","elType":"widget"}],"isInner":true,"elType":"column"}],"isInner":true,"elType":"section"}],"isInner":false,"elType":"column"}],"isInner":false,"elType":"section"}]}