{"version":"0.4","title":"Zakra Spa V2 &#8211; News Section","type":"section","content":[{"id":"705479fd","settings":{"background_background":"classic","background_color":"#f8f9f6","background_image":{"url":"http:\/\/easy-elephant.w5.wpsandbox.pro\/wp-content\/uploads\/2019\/09\/stone-bg.png","id":704},"background_position":"bottom left","background_repeat":"no-repeat","padding":{"unit":"px","top":"130","right":"0","bottom":"130","left":"0","isLinked":false},"padding_tablet":{"unit":"px","top":"80","right":"0","bottom":"80","left":"0","isLinked":false},"padding_mobile":{"unit":"px","top":"70","right":"0","bottom":"70","left":"0","isLinked":false}},"elements":[{"id":"1acb196d","settings":{"_column_size":100,"padding_mobile":{"unit":"px","top":"0","right":"0","bottom":"0","left":"0","isLinked":false}},"elements":[{"id":"59e16d6d","settings":[],"elements":[{"id":"57c5331b","settings":{"_column_size":100,"_inline_size":null},"elements":[{"id":"1bfbee54","settings":{"title":"Welcome to Zakra Spa Center","header_size":"h6","align":"center","title_color":"#343a40","typography_typography":"custom","typography_font_family":"Poppins","typography_font_size":{"unit":"px","size":14,"sizes":[]},"typography_font_weight":"400","typography_text_transform":"uppercase","typography_letter_spacing":{"unit":"px","size":1,"sizes":[]}},"elements":[],"isInner":false,"widgetType":"heading","elType":"widget"}],"isInner":true,"elType":"column"}],"isInner":true,"elType":"section"},{"id":"413d55c2","settings":{"title":"latest news and events","align":"center","title_color":"#212529","typography_typography":"custom","typography_font_family":"Playfair Display","typography_font_size":{"unit":"px","size":34,"sizes":[]},"typography_font_weight":"700","typography_text_transform":"uppercase","typography_letter_spacing":{"unit":"px","size":3,"sizes":[]},"typography_line_height":{"unit":"em","size":1.3,"sizes":[]},"_margin":{"unit":"px","top":"0","right":"0","bottom":"0","left":"0","isLinked":false},"typography_font_size_mobile":{"unit":"px","size":30,"sizes":[]}},"elements":[],"isInner":false,"widgetType":"heading","elType":"widget"},{"id":"44a9a6eb","settings":{"text":"I am a Divider","icon":"fa fa-pagelines","divider_stacked":"","icon_size":{"unit":"px","size":50,"sizes":[]},"divider_color":"#212529","divider_length":{"unit":"px","size":100,"sizes":[]},"divider_weight":{"unit":"px","size":1,"sizes":[]},"icon_font_size":{"unit":"px","size":34,"sizes":[]},"_margin":{"unit":"px","top":"-5","right":"0","bottom":"0","left":"0","isLinked":false}},"elements":[],"isInner":false,"widgetType":"elementor-companion-divider","elType":"widget"},{"id":"34df2948","settings":{"structure":"30","background_background":"classic","background_image":{"url":"http:\/\/easy-elephant.w5.wpsandbox.pro\/wp-content\/uploads\/2019\/09\/leaf-2-bg.png","id":703},"background_position":"top right","background_repeat":"no-repeat","background_size":"auto","margin":{"unit":"px","top":"0","right":0,"bottom":"0","left":0,"isLinked":false},"padding":{"unit":"px","top":"70","right":"0","bottom":"0","left":"0","isLinked":false},"padding_tablet":{"unit":"px","top":"45","right":"0","bottom":"0","left":"0","isLinked":false},"padding_mobile":{"unit":"px","top":"30","right":"15","bottom":"0","left":"15","isLinked":false}},"elements":[{"id":"5d60b3b8","settings":{"_column_size":33,"_inline_size":null,"background_background":"classic","background_color":"#fff","margin":{"unit":"px","top":"0","right":"15","bottom":"0","left":"15","isLinked":false},"padding":{"unit":"px","top":"0","right":"0","bottom":"0","left":"0","isLinked":false},"_inline_size_tablet":50,"margin_tablet":{"unit":"px","top":"0","right":"5","bottom":"0","left":"5","isLinked":false},"margin_mobile":{"unit":"px","top":"0","right":"0","bottom":"0","left":"0","isLinked":false},"padding_tablet":{"unit":"px","top":"0","right":"0","bottom":"0","left":"0","isLinked":false}},"elements":[{"id":"4534aa4d","settings":{"image":{"url":"https:\/\/zakrademos.com\/spa-v2\/wp-content\/uploads\/sites\/26\/2019\/09\/blog-1-2.jpg","id":700},"image_size":"full","width":{"unit":"%","size":100,"sizes":[]},"_margin":{"unit":"px","top":"0","right":"0","bottom":"0","left":"0","isLinked":false},"_padding":{"unit":"px","top":"0","right":"0","bottom":"0","left":"0","isLinked":false},"_margin_tablet":{"unit":"px","top":"0","right":"0","bottom":"0","left":"0","isLinked":false},"_padding_tablet":{"unit":"px","top":"0","right":"0","bottom":"0","left":"0","isLinked":false},"link_to":"custom","link":{"url":"#","is_external":"","nofollow":""},"align_mobile":"left","width_mobile":{"unit":"%","size":100,"sizes":[]},"space_mobile":{"unit":"%","size":100,"sizes":[]}},"elements":[],"isInner":false,"widgetType":"image","elType":"widget"},{"id":"332a84d6","settings":{"title":"Lorem ipsum dolor sit amet elit","header_size":"h4","title_color":"#212529","typography_typography":"custom","typography_font_family":"Playfair Display","typography_font_size":{"unit":"px","size":22,"sizes":[]},"typography_font_weight":"700","_margin":{"unit":"px","top":"20","right":"0","bottom":"0","left":"0","isLinked":false},"_padding":{"unit":"px","top":"0","right":"30","bottom":"0","left":"30","isLinked":false},"typography_line_height":{"unit":"em","size":1.3,"sizes":[]},"link":{"url":"#","is_external":"","nofollow":""}},"elements":[],"isInner":false,"widgetType":"heading","elType":"widget"},{"id":"416a1e86","settings":{"view":"inline","icon_list":[{"text":"Michael ","selected_icon":{"value":"fas fa-user","library":"fa-solid"},"_id":"f8fb011","link":{"url":"","is_external":"","nofollow":""},"icon":"fa fa-check"},{"text":"03 May, 2019","selected_icon":{"value":"far fa-calendar-alt","library":"fa-regular"},"_id":"eed98f7","link":{"url":"","is_external":"","nofollow":""},"icon":"fa fa-check"},{"text":"7 Comments","selected_icon":{"value":"fas fa-comment","library":"fa-solid"},"_id":"8af6b5a","link":{"url":"","is_external":"","nofollow":""},"icon":"fa fa-check"}],"space_between":{"unit":"px","size":30,"sizes":[]},"icon_color":"#2d2a27","icon_size":{"unit":"px","size":12,"sizes":[]},"text_color":"#212529","icon_typography_typography":"custom","icon_typography_font_family":"Poppins","icon_typography_font_size":{"unit":"px","size":10,"sizes":[]},"icon_typography_font_weight":"400","_padding":{"unit":"px","top":"0","right":"30","bottom":"0","left":"30","isLinked":false}},"elements":[],"isInner":false,"widgetType":"icon-list","elType":"widget"},{"id":"5877b3e0","settings":{"title":"Lorem ipsum dolor sit amet, consectetur adipiscing elit. Quisque non ante leo and aenean consequat blandit diam.","header_size":"p","title_color":"#343a40","typography_typography":"custom","typography_font_family":"Poppins","typography_font_size":{"unit":"px","size":14,"sizes":[]},"typography_font_weight":"400","typography_line_height":{"unit":"em","size":1.875,"sizes":[]},"_margin":{"unit":"px","top":"0","right":"0","bottom":"0","left":"0","isLinked":false},"_padding":{"unit":"px","top":"0","right":"30","bottom":"0","left":"30","isLinked":false}},"elements":[],"isInner":false,"widgetType":"heading","elType":"widget"},{"id":"301c7824","settings":{"text":"Read more","align":"left","size":"md","typography_typography":"custom","typography_font_family":"Playfair Display","typography_font_size":{"unit":"px","size":10,"sizes":[]},"typography_font_weight":"700","typography_text_transform":"uppercase","typography_letter_spacing":{"unit":"px","size":1,"sizes":[]},"border_radius":{"unit":"px","top":"0","right":"0","bottom":"0","left":"0","isLinked":true},"text_padding":{"unit":"px","top":"12","right":"25","bottom":"12","left":"25","isLinked":false},"_margin":{"unit":"px","top":"5","right":"0","bottom":"45","left":"0","isLinked":false},"_padding":{"unit":"px","top":"0","right":"30","bottom":"0","left":"30","isLinked":false},"button_background_hover_color":"#000000"},"elements":[],"isInner":false,"widgetType":"button","elType":"widget"}],"isInner":true,"elType":"column"},{"id":"157bd63d","settings":{"_column_size":33,"_inline_size":null,"background_background":"classic","background_color":"#fff","margin":{"unit":"px","top":"0","right":"15","bottom":"0","left":"15","isLinked":false},"padding":{"unit":"px","top":"0","right":"0","bottom":"0","left":"0","isLinked":false},"_inline_size_tablet":50,"margin_tablet":{"unit":"px","top":"0","right":"5","bottom":"0","left":"5","isLinked":false},"margin_mobile":{"unit":"px","top":"15","right":"0","bottom":"0","left":"0","isLinked":false},"padding_tablet":{"unit":"px","top":"0","right":"0","bottom":"0","left":"0","isLinked":false}},"elements":[{"id":"5af791d5","settings":{"image":{"url":"https:\/\/zakrademos.com\/spa-v2\/wp-content\/uploads\/sites\/26\/2019\/09\/blog-2.jpg","id":701},"image_size":"full","width":{"unit":"%","size":100,"sizes":[]},"_margin":{"unit":"px","top":"0","right":"0","bottom":"0","left":"0","isLinked":false},"_padding":{"unit":"px","top":"0","right":"0","bottom":"0","left":"0","isLinked":false},"link_to":"custom","link":{"url":"#","is_external":"","nofollow":""},"align_mobile":"left","width_mobile":{"unit":"%","size":100,"sizes":[]}},"elements":[],"isInner":false,"widgetType":"image","elType":"widget"},{"id":"b6e7971","settings":{"title":"Lorem ipsum dolor sit amet elit","header_size":"h4","title_color":"#212529","typography_typography":"custom","typography_font_family":"Playfair Display","typography_font_size":{"unit":"px","size":22,"sizes":[]},"typography_font_weight":"700","_margin":{"unit":"px","top":"20","right":"0","bottom":"0","left":"0","isLinked":false},"_padding":{"unit":"px","top":"0","right":"30","bottom":"0","left":"30","isLinked":false},"typography_line_height":{"unit":"em","size":1.3,"sizes":[]},"link":{"url":"#","is_external":"","nofollow":""}},"elements":[],"isInner":false,"widgetType":"heading","elType":"widget"},{"id":"6a8d01fa","settings":{"view":"inline","icon_list":[{"text":"Michael ","selected_icon":{"value":"fas fa-user","library":"fa-solid"},"_id":"f8fb011","link":{"url":"","is_external":"","nofollow":""},"icon":"fa fa-check"},{"text":"03 May, 2019","selected_icon":{"value":"far fa-calendar-alt","library":"fa-regular"},"_id":"eed98f7","link":{"url":"","is_external":"","nofollow":""},"icon":"fa fa-check"},{"text":"7 Comments","selected_icon":{"value":"fas fa-comment","library":"fa-solid"},"_id":"8af6b5a","link":{"url":"","is_external":"","nofollow":""},"icon":"fa fa-check"}],"space_between":{"unit":"px","size":30,"sizes":[]},"icon_color":"#2d2a27","icon_size":{"unit":"px","size":12,"sizes":[]},"text_color":"#212529","icon_typography_typography":"custom","icon_typography_font_family":"Poppins","icon_typography_font_size":{"unit":"px","size":10,"sizes":[]},"icon_typography_font_weight":"400","_padding":{"unit":"px","top":"0","right":"30","bottom":"0","left":"30","isLinked":false}},"elements":[],"isInner":false,"widgetType":"icon-list","elType":"widget"},{"id":"1021fa8c","settings":{"title":"Lorem ipsum dolor sit amet, consectetur adipiscing elit. Quisque non ante leo and aenean consequat blandit diam.","header_size":"p","title_color":"#343a40","typography_typography":"custom","typography_font_family":"Poppins","typography_font_size":{"unit":"px","size":14,"sizes":[]},"typography_font_weight":"400","typography_line_height":{"unit":"em","size":1.875,"sizes":[]},"_margin":{"unit":"px","top":"0","right":"0","bottom":"0","left":"0","isLinked":false},"_padding":{"unit":"px","top":"0","right":"30","bottom":"0","left":"30","isLinked":false}},"elements":[],"isInner":false,"widgetType":"heading","elType":"widget"},{"id":"20a8a6a6","settings":{"text":"Read more","align":"left","size":"md","typography_typography":"custom","typography_font_family":"Playfair Display","typography_font_size":{"unit":"px","size":10,"sizes":[]},"typography_font_weight":"700","typography_text_transform":"uppercase","typography_letter_spacing":{"unit":"px","size":1,"sizes":[]},"border_radius":{"unit":"px","top":"0","right":"0","bottom":"0","left":"0","isLinked":true},"text_padding":{"unit":"px","top":"12","right":"25","bottom":"12","left":"25","isLinked":false},"_margin":{"unit":"px","top":"5","right":"0","bottom":"45","left":"0","isLinked":false},"_padding":{"unit":"px","top":"0","right":"30","bottom":"0","left":"30","isLinked":false},"button_background_hover_color":"#000000"},"elements":[],"isInner":false,"widgetType":"button","elType":"widget"}],"isInner":true,"elType":"column"},{"id":"2842cd50","settings":{"_column_size":33,"_inline_size":null,"background_background":"classic","background_color":"#fff","margin":{"unit":"px","top":"0","right":"15","bottom":"0","left":"15","isLinked":false},"padding":{"unit":"px","top":"0","right":"0","bottom":"0","left":"0","isLinked":false},"_inline_size_tablet":50,"margin_tablet":{"unit":"px","top":"10","right":"5","bottom":"0","left":"5","isLinked":false},"margin_mobile":{"unit":"px","top":"15","right":"0","bottom":"0","left":"0","isLinked":false},"padding_tablet":{"unit":"px","top":"0","right":"0","bottom":"0","left":"0","isLinked":false}},"elements":[{"id":"2858b0f2","settings":{"image":{"url":"https:\/\/zakrademos.com\/spa-v2\/wp-content\/uploads\/sites\/26\/2019\/09\/blog-3-1.jpg","id":702},"image_size":"full","width":{"unit":"%","size":100,"sizes":[]},"_margin":{"unit":"px","top":"0","right":"0","bottom":"0","left":"0","isLinked":false},"_padding":{"unit":"px","top":"0","right":"0","bottom":"0","left":"0","isLinked":false},"link_to":"custom","link":{"url":"#","is_external":"","nofollow":""},"align_mobile":"left","width_mobile":{"unit":"%","size":100,"sizes":[]}},"elements":[],"isInner":false,"widgetType":"image","elType":"widget"},{"id":"2c3b7752","settings":{"title":"Lorem ipsum dolor sit amet elit","header_size":"h4","title_color":"#212529","typography_typography":"custom","typography_font_family":"Playfair Display","typography_font_size":{"unit":"px","size":22,"sizes":[]},"typography_font_weight":"700","_margin":{"unit":"px","top":"20","right":"0","bottom":"0","left":"0","isLinked":false},"_padding":{"unit":"px","top":"0","right":"30","bottom":"0","left":"30","isLinked":false},"typography_line_height":{"unit":"em","size":1.3,"sizes":[]},"link":{"url":"#","is_external":"","nofollow":""}},"elements":[],"isInner":false,"widgetType":"heading","elType":"widget"},{"id":"8978fda","settings":{"view":"inline","icon_list":[{"text":"Michael ","selected_icon":{"value":"fas fa-user","library":"fa-solid"},"_id":"f8fb011","link":{"url":"","is_external":"","nofollow":""},"icon":"fa fa-check"},{"text":"03 May, 2019","selected_icon":{"value":"far fa-calendar-alt","library":"fa-regular"},"_id":"eed98f7","link":{"url":"","is_external":"","nofollow":""},"icon":"fa fa-check"},{"text":"7 Comments","selected_icon":{"value":"fas fa-comment","library":"fa-solid"},"_id":"8af6b5a","link":{"url":"","is_external":"","nofollow":""},"icon":"fa fa-check"}],"space_between":{"unit":"px","size":30,"sizes":[]},"icon_color":"#2d2a27","icon_size":{"unit":"px","size":12,"sizes":[]},"text_color":"#212529","icon_typography_typography":"custom","icon_typography_font_family":"Poppins","icon_typography_font_size":{"unit":"px","size":10,"sizes":[]},"icon_typography_font_weight":"400","_padding":{"unit":"px","top":"0","right":"30","bottom":"0","left":"30","isLinked":false}},"elements":[],"isInner":false,"widgetType":"icon-list","elType":"widget"},{"id":"1f99cc95","settings":{"title":"Lorem ipsum dolor sit amet, consectetur adipiscing elit. Quisque non ante leo and aenean consequat blandit diam.","header_size":"p","title_color":"#343a40","typography_typography":"custom","typography_font_family":"Poppins","typography_font_size":{"unit":"px","size":14,"sizes":[]},"typography_font_weight":"400","typography_line_height":{"unit":"em","size":1.875,"sizes":[]},"_margin":{"unit":"px","top":"0","right":"0","bottom":"0","left":"0","isLinked":false},"_padding":{"unit":"px","top":"0","right":"30","bottom":"0","left":"30","isLinked":false}},"elements":[],"isInner":false,"widgetType":"heading","elType":"widget"},{"id":"79821fd5","settings":{"text":"Read more","align":"left","size":"md","typography_typography":"custom","typography_font_family":"Playfair Display","typography_font_size":{"unit":"px","size":10,"sizes":[]},"typography_font_weight":"700","typography_text_transform":"uppercase","typography_letter_spacing":{"unit":"px","size":1,"sizes":[]},"border_radius":{"unit":"px","top":"0","right":"0","bottom":"0","left":"0","isLinked":true},"text_padding":{"unit":"px","top":"12","right":"25","bottom":"12","left":"25","isLinked":false},"_margin":{"unit":"px","top":"5","right":"0","bottom":"45","left":"0","isLinked":false},"_padding":{"unit":"px","top":"0","right":"30","bottom":"0","left":"30","isLinked":false},"background_color":"#2d2a27","button_background_hover_color":"#000000"},"elements":[],"isInner":false,"widgetType":"button","elType":"widget"}],"isInner":true,"elType":"column"}],"isInner":true,"elType":"section"},{"id":"33772524","settings":{"margin":{"unit":"px","top":"90","right":0,"bottom":"0","left":0,"isLinked":false},"margin_mobile":{"unit":"px","top":"50","right":0,"bottom":"0","left":0,"isLinked":false}},"elements":[{"id":"630f21c","settings":{"_column_size":100,"_inline_size":null},"elements":[{"id":"30c6ca1f","settings":{"text":"Explore all","align":"center","size":"md","typography_typography":"custom","typography_font_family":"Playfair Display","typography_font_size":{"unit":"px","size":12,"sizes":[]},"typography_font_weight":"700","typography_text_transform":"uppercase","typography_letter_spacing":{"unit":"px","size":1,"sizes":[]},"border_radius":{"unit":"px","top":"0","right":"0","bottom":"0","left":"0","isLinked":true},"text_padding":{"unit":"px","top":"18","right":"45","bottom":"18","left":"45","isLinked":false},"button_background_hover_color":"#000000"},"elements":[],"isInner":false,"widgetType":"button","elType":"widget"}],"isInner":true,"elType":"column"}],"isInner":true,"elType":"section"}],"isInner":false,"elType":"column"}],"isInner":false,"elType":"section"}]}