{"version":"0.4","title":"Zakra App V2 &#8211; Front Page","type":"page","content":[{"id":"3cc6d8cc","settings":{"structure":"20","background_background":"classic","background_image":{"url":"https:\/\/zakrademos.com\/app-v2\/wp-content\/uploads\/sites\/40\/2019\/10\/banner.jpg","id":66},"background_position":"center center","background_attachment":"scroll","background_repeat":"no-repeat","background_size":"cover","background_overlay_background":"classic","background_overlay_color":"#f35488","background_overlay_image":{"url":"https:\/\/zakrademos.com\/app-v2\/wp-content\/uploads\/sites\/40\/2019\/10\/half-left-circle.png","id":77},"background_overlay_position":"top left","background_overlay_repeat":"no-repeat","background_overlay_size":"initial","background_overlay_bg_width":{"unit":"%","size":18,"sizes":[]},"background_overlay_opacity":{"unit":"px","size":0.88,"sizes":[]}},"elements":[{"id":"3298e9a5","settings":{"_column_size":50,"_inline_size":null,"padding":{"unit":"px","top":"0","right":"0","bottom":"0","left":"110","isLinked":false},"_inline_size_tablet":50,"padding_tablet":{"unit":"px","top":"240","right":"0","bottom":"130","left":"50","isLinked":false},"padding_mobile":{"unit":"px","top":"160","right":"15","bottom":"10","left":"15","isLinked":false},"content_position_tablet":"center","content_position":"center","background_background":"classic"},"elements":[{"id":"3d737f29","settings":{"first_text":"Mobile apps","second_text":"is your safe","headings_stacked":"yes","first_color":"#ffffff","second_color":"#ffffff","headings_gap":{"unit":"px","size":15,"sizes":[]},"first_typography_typography":"custom","first_typography_font_size":{"unit":"px","size":65,"sizes":[]},"first_typography_font_weight":"900","first_typography_line_height":{"unit":"em","size":0.95,"sizes":[]},"first_text_shadow_text_shadow_type":"yes","first_text_shadow_text_shadow":{"horizontal":0,"vertical":0,"blur":"","color":"rgba(0,0,0,0.3)"},"second_typography_typography":"custom","second_typography_font_size":{"unit":"px","size":65,"sizes":[]},"second_typography_font_weight":"900","second_typography_line_height":{"unit":"em","size":0.95,"sizes":[]},"second_text_shadow_text_shadow_type":"yes","second_text_shadow_text_shadow":{"horizontal":0,"vertical":0,"blur":"","color":"rgba(0,0,0,0.3)"},"headings_alignment_mobile":"center","first_typography_font_size_tablet":{"unit":"px","size":52,"sizes":[]},"first_typography_font_size_mobile":{"unit":"px","size":48,"sizes":[]},"second_typography_font_size_tablet":{"unit":"px","size":52,"sizes":[]},"second_typography_font_size_mobile":{"unit":"px","size":48,"sizes":[]}},"elements":[],"isInner":false,"widgetType":"elementor-companion-dual-heading","elType":"widget"},{"id":"5eeec463","settings":{"title":"Lorem ipsum dolor sit amet consectetur.","align":"left","title_color":"#ffffff","typography_typography":"custom","typography_font_size":{"unit":"px","size":22,"sizes":[]},"typography_font_weight":"400","typography_line_height":{"unit":"em","size":2,"sizes":[]},"text_shadow_text_shadow_type":"yes","text_shadow_text_shadow":{"horizontal":0,"vertical":0,"blur":"","color":"rgba(0,0,0,0.3)"},"_margin":{"unit":"px","top":"-17","right":"0","bottom":"0","left":"0","isLinked":false},"align_mobile":"center","typography_font_size_mobile":{"unit":"px","size":16,"sizes":[]},"typography_line_height_tablet":{"unit":"em","size":1.3,"sizes":[]}},"elements":[],"isInner":false,"widgetType":"heading","elType":"widget"},{"id":"758de251","settings":[],"elements":[{"id":"215b9a10","settings":{"_column_size":100,"_inline_size":null,"align_mobile":"center","padding":{"unit":"px","top":"0","right":"0","bottom":"0","left":"0","isLinked":false}},"elements":[{"id":"726b74ad","settings":{"text":"LEARN MORE","typography_typography":"custom","typography_font_size":{"unit":"px","size":16,"sizes":[]},"typography_font_weight":"900","text_shadow_text_shadow_type":"yes","text_shadow_text_shadow":{"horizontal":0,"vertical":0,"blur":"","color":"rgba(0,0,0,0.3)"},"button_text_color":"#ffffff","background_color":"rgba(0,0,0,0)","hover_color":"#222222","button_background_hover_color":"#ffffff","button_hover_border_color":"#ffffff","border_border":"solid","border_width":{"unit":"px","top":"3","right":"3","bottom":"3","left":"3","isLinked":true},"border_color":"#ffffff","border_radius":{"unit":"px","top":"8","right":"8","bottom":"8","left":"8","isLinked":true},"text_padding":{"unit":"px","top":"17","right":"41","bottom":"17","left":"41","isLinked":false},"text_padding_tablet":{"unit":"px","top":"13","right":"17","bottom":"13","left":"17","isLinked":false},"align":"left","align_mobile":"center","_margin":{"unit":"px","top":"0","right":"10","bottom":"0","left":"0","isLinked":false},"link":{"url":"https:\/\/zakrademos.com\/app-v2\/about\/","is_external":"on","nofollow":""},"_element_width":"auto","_element_vertical_align":"flex-start"},"elements":[],"isInner":false,"widgetType":"button","elType":"widget"},{"id":"5f71116f","settings":{"text":"Get App Now","typography_typography":"custom","typography_font_size":{"unit":"px","size":16,"sizes":[]},"typography_font_weight":"900","text_shadow_text_shadow_type":"yes","text_shadow_text_shadow":{"horizontal":0,"vertical":0,"blur":"","color":"rgba(0,0,0,0.3)"},"button_text_color":"#222222","background_color":"#ffffff","hover_color":"#ffffff","button_background_hover_color":"rgba(0,0,0,0)","button_hover_border_color":"#ffffff","border_border":"solid","border_width":{"unit":"px","top":"3","right":"3","bottom":"3","left":"3","isLinked":true},"border_color":"#ffffff","border_radius":{"unit":"px","top":"8","right":"8","bottom":"8","left":"8","isLinked":true},"text_padding":{"unit":"px","top":"17","right":"41","bottom":"17","left":"41","isLinked":false},"text_padding_tablet":{"unit":"px","top":"13","right":"17","bottom":"13","left":"17","isLinked":false},"align_mobile":"center","link":{"url":"#","is_external":"on","nofollow":""},"_element_width":"auto"},"elements":[],"isInner":false,"widgetType":"button","elType":"widget"}],"isInner":true,"elType":"column"}],"isInner":true,"elType":"section"}],"isInner":false,"elType":"column"},{"id":"50c2e003","settings":{"_column_size":50,"_inline_size":null,"background_background":"classic","background_image":{"url":"http:\/\/dandelion-camel.w6.wpsandbox.pro\/wp-content\/uploads\/2019\/10\/top-circle.png","id":69},"background_position":"top right","background_attachment":"scroll","background_repeat":"no-repeat","background_size":"initial","background_bg_width":{"unit":"%","size":74,"sizes":[]},"_inline_size_tablet":50,"content_position_tablet":"center","content_position_mobile":"top","padding_mobile":{"unit":"px","top":"0","right":"0","bottom":"0","left":"0","isLinked":false},"content_position":"center","margin":{"unit":"px","top":"90","right":"0","bottom":"0","left":"0","isLinked":false},"margin_mobile":{"unit":"px","top":"60","right":"0","bottom":"0","left":"0","isLinked":false}},"elements":[{"id":"5787a5f5","settings":[],"elements":[{"id":"2b9fb5e0","settings":{"_column_size":100,"_inline_size":null,"padding":{"unit":"px","top":"0","right":"0","bottom":"0","left":"0","isLinked":false},"_inline_size_tablet":100,"margin_mobile":{"unit":"px","top":"0","right":"15","bottom":"0","left":"15","isLinked":false}},"elements":[{"id":"16edf1ea","settings":{"image":{"url":"https:\/\/zakrademos.com\/app-v2\/wp-content\/uploads\/sites\/40\/2019\/10\/mobile-width-3-circle.png","id":70}},"elements":[],"isInner":false,"widgetType":"image","elType":"widget"}],"isInner":true,"elType":"column"}],"isInner":true,"elType":"section"}],"isInner":false,"elType":"column"}],"isInner":false,"elType":"section"},{"id":"3116b7f3","settings":[],"elements":[{"id":"1bae8e73","settings":{"_column_size":100},"elements":[{"id":"2fe78a39","settings":{"space":{"unit":"px","size":190,"sizes":[]},"space_mobile":{"unit":"px","size":80,"sizes":[]},"space_tablet":{"unit":"px","size":110,"sizes":[]}},"elements":[],"isInner":false,"widgetType":"spacer","elType":"widget"},{"id":"2a819d4a","settings":{"structure":"50"},"elements":[{"id":"76fb6ac","settings":{"_column_size":20,"_inline_size":34.988,"padding":{"unit":"px","top":"0","right":"0","bottom":"0","left":"0","isLinked":false},"_inline_size_tablet":31,"_inline_size_mobile":15},"elements":[{"id":"7d1c9528","settings":{"divider_type":"normal","text":"I am a Divider","divider_alignment":"right","divider_stacked":"yes","divider_direction":"vertical","icon_position":"left","icon_border_width":{"unit":"px","top":"0","right":"0","bottom":"0","left":"0","isLinked":true},"individual_style":"","divider_color":"#eb3970","divider_length":{"unit":"px","size":66,"sizes":[]},"divider_weight":{"unit":"px","size":2,"sizes":[]},"divider_length_tablet":{"unit":"px","size":45,"sizes":[]}},"elements":[],"isInner":false,"widgetType":"elementor-companion-divider","elType":"widget"}],"isInner":true,"elType":"column"},{"id":"3cb35468","settings":{"_column_size":20,"_inline_size":4.766,"padding":{"unit":"px","top":"0","right":"0","bottom":"0","left":"0","isLinked":false},"_inline_size_tablet":6,"_inline_size_mobile":10},"elements":[{"id":"77cc802e","settings":{"divider_type":"normal","text":"I am a Divider","divider_alignment":"left","divider_stacked":"yes","icon_position":"left","icon_border_width":{"unit":"px","top":"0","right":"0","bottom":"0","left":"0","isLinked":true},"individual_style":"","divider_color":"#eb3970","divider_length":{"unit":"px","size":66,"sizes":[]},"divider_length_tablet":{"unit":"px","size":45,"sizes":[]}},"elements":[],"isInner":false,"widgetType":"elementor-companion-divider","elType":"widget"}],"isInner":true,"elType":"column"},{"id":"161bc991","settings":{"_column_size":20,"_inline_size":20.399,"_inline_size_tablet":24,"_inline_size_mobile":50},"elements":[{"id":"57bbc69b","settings":{"title":"About us","align":"center","title_color":"#eb3970","typography_typography":"custom","typography_font_size":{"unit":"px","size":50,"sizes":[]},"typography_font_weight":"900","text_shadow_text_shadow_type":"yes","text_shadow_text_shadow":{"horizontal":0,"vertical":0,"blur":"","color":"rgba(0,0,0,0.3)"},"_padding":{"unit":"px","top":"15","right":"0","bottom":"15","left":"0","isLinked":false},"typography_font_size_tablet":{"unit":"px","size":38,"sizes":[]},"typography_font_size_mobile":{"unit":"px","size":32,"sizes":[]}},"elements":[],"isInner":false,"widgetType":"heading","elType":"widget"}],"isInner":true,"elType":"column"},{"id":"3a26e533","settings":{"_column_size":20,"_inline_size":4.862,"content_position":"bottom","border_border":"solid","border_width":{"unit":"px","top":"0","right":"0","bottom":"0","left":"0","isLinked":true},"padding":{"unit":"px","top":"0","right":"0","bottom":"0","left":"0","isLinked":true},"_inline_size_tablet":6,"_inline_size_mobile":10},"elements":[{"id":"4b14b331","settings":{"divider_type":"normal","text":"I am a Divider","divider_alignment":"right","divider_stacked":"yes","icon_position":"left","icon_border_width":{"unit":"px","top":"0","right":"0","bottom":"0","left":"0","isLinked":true},"individual_style":"","divider_color":"#eb3970","divider_length":{"unit":"px","size":66,"sizes":[]},"divider_length_tablet":{"unit":"px","size":45,"sizes":[]}},"elements":[],"isInner":false,"widgetType":"elementor-companion-divider","elType":"widget"}],"isInner":true,"elType":"column"},{"id":"78f3bc0e","settings":{"_column_size":20,"_inline_size":34.985,"content_position":"bottom","padding":{"unit":"px","top":"0","right":"0","bottom":"0","left":"0","isLinked":false},"_inline_size_tablet":31,"_inline_size_mobile":15},"elements":[{"id":"7f899562","settings":{"divider_type":"normal","text":"I am a Divider","divider_alignment":"left","divider_stacked":"yes","divider_direction":"vertical","icon_position":"left","icon_border_width":{"unit":"px","top":"0","right":"0","bottom":"0","left":"0","isLinked":true},"individual_style":"","divider_color":"#eb3970","divider_length":{"unit":"px","size":66,"sizes":[]},"divider_weight":{"unit":"px","size":2,"sizes":[]},"divider_length_tablet":{"unit":"px","size":45,"sizes":[]}},"elements":[],"isInner":false,"widgetType":"elementor-companion-divider","elType":"widget"}],"isInner":true,"elType":"column"}],"isInner":true,"elType":"section"},{"id":"62830042","settings":{"space":{"unit":"px","size":90,"sizes":[]},"space_tablet":{"unit":"px","size":50,"sizes":[]},"space_mobile":{"unit":"px","size":35,"sizes":[]}},"elements":[],"isInner":false,"widgetType":"spacer","elType":"widget"}],"isInner":false,"elType":"column"}],"isInner":false,"elType":"section"},{"id":"2c79a736","settings":{"structure":"30"},"elements":[{"id":"f95169e","settings":{"_column_size":33,"_inline_size":50,"background_background":"classic","background_image":{"url":"https:\/\/zakrademos.com\/app-v2\/wp-content\/uploads\/sites\/40\/2019\/10\/about-bg.png","id":105},"background_position":"top center","background_attachment":"scroll","background_repeat":"no-repeat","background_size":"auto","background_size_tablet":"initial","background_size_mobile":"initial","background_bg_width_tablet":{"unit":"px","size":369,"sizes":[]},"background_bg_width_mobile":{"unit":"px","size":339,"sizes":[]},"margin":{"unit":"px","top":"0","right":"0","bottom":"0","left":"-40","isLinked":false},"margin_tablet":{"unit":"px","top":"0","right":"0","bottom":"0","left":"0","isLinked":true}},"elements":[{"id":"6a877457","settings":{"image":{"url":"https:\/\/zakrademos.com\/app-v2\/wp-content\/uploads\/sites\/40\/2019\/10\/mobile-screenshot.png","id":104},"_margin":{"unit":"px","top":"78","right":"68","bottom":"0","left":"0","isLinked":false}},"elements":[],"isInner":false,"widgetType":"image","elType":"widget"}],"isInner":false,"elType":"column"},{"id":"447777df","settings":{"_column_size":33,"_inline_size":9.666,"_inline_size_tablet":7},"elements":[],"isInner":false,"elType":"column"},{"id":"67fa542c","settings":{"_column_size":33,"_inline_size":40,"margin":{"unit":"px","top":"85","right":"0","bottom":"0","left":"0","isLinked":false},"padding":{"unit":"px","top":"0","right":"0","bottom":"0","left":"0","isLinked":false},"margin_tablet":{"unit":"px","top":"40","right":"0","bottom":"0","left":"0","isLinked":false},"margin_mobile":{"unit":"px","top":"40","right":"15","bottom":"0","left":"15","isLinked":false}},"elements":[{"id":"758edf7e","settings":{"title":"Lorem Ipsum is simply dummy text of the printing and typesetting industry. Lorem Ipsum has been the industry's standard dummy.","align":"left","title_color":"#222222","typography_typography":"custom","typography_font_size":{"unit":"px","size":18,"sizes":[]},"typography_font_weight":"700","typography_line_height":{"unit":"em","size":1.67,"sizes":[]},"text_shadow_text_shadow_type":"yes","text_shadow_text_shadow":{"horizontal":0,"vertical":0,"blur":"","color":"rgba(0,0,0,0.3)"},"_padding":{"unit":"px","top":"0","right":"10","bottom":"0","left":"0","isLinked":false},"align_mobile":"center"},"elements":[],"isInner":false,"widgetType":"heading","elType":"widget"},{"id":"4d0895c7","settings":{"title":"Lorem Ipsum is simply dummy text of the printing and typesetting industry. Lorem Ipsum has been the industry's standard dummy text ever since the 1500s, when an unknown printer took a galley of type and scrambled it to make a type specimen book. It has survived not only five centuries, but also the leap into electronic typesetting.","align":"left","title_color":"#222222","typography_typography":"custom","typography_font_size":{"unit":"px","size":18,"sizes":[]},"typography_font_weight":"400","typography_line_height":{"unit":"em","size":1.67,"sizes":[]},"text_shadow_text_shadow_type":"yes","text_shadow_text_shadow":{"horizontal":0,"vertical":0,"blur":"","color":"rgba(0,0,0,0.3)"},"_margin":{"unit":"px","top":"5","right":"0","bottom":"0","left":"0","isLinked":false},"align_mobile":"center"},"elements":[],"isInner":false,"widgetType":"heading","elType":"widget"},{"id":"23663c42","settings":{"text":"DISCOVER MORE","typography_typography":"custom","typography_font_size":{"unit":"px","size":16,"sizes":[]},"typography_font_weight":"900","text_shadow_text_shadow_type":"yes","text_shadow_text_shadow":{"horizontal":0,"vertical":0,"blur":"","color":"rgba(0,0,0,0.3)"},"button_text_color":"#ffffff","background_color":"#f35488","hover_color":"#222222","button_background_hover_color":"#ffffff","button_hover_border_color":"#f35488","border_border":"solid","border_width":{"unit":"px","top":"1","right":"1","bottom":"1","left":"1","isLinked":true},"border_color":"#ffffff","border_radius":{"unit":"px","top":"9","right":"9","bottom":"9","left":"9","isLinked":true},"text_padding":{"unit":"px","top":"20","right":"30","bottom":"20","left":"30","isLinked":false},"_margin":{"unit":"px","top":"20","right":"0","bottom":"0","left":"0","isLinked":false},"align_mobile":"center","link":{"url":"https:\/\/zakrademos.com\/app-v2\/about\/","is_external":"on","nofollow":""}},"elements":[],"isInner":false,"widgetType":"button","elType":"widget"}],"isInner":false,"elType":"column"}],"isInner":false,"elType":"section"},{"id":"664291d1","settings":{"layout":"full_width"},"elements":[{"id":"5e4e4138","settings":{"_column_size":100,"padding":{"unit":"px","top":"0","right":"0","bottom":"0","left":"0","isLinked":false}},"elements":[{"id":"44c1d653","settings":{"space":{"unit":"px","size":60,"sizes":[]}},"elements":[],"isInner":false,"widgetType":"spacer","elType":"widget"},{"id":"45eec529","settings":{"structure":"30","padding_tablet":{"unit":"px","top":"0","right":"15","bottom":"0","left":"15","isLinked":false}},"elements":[{"id":"5f1290db","settings":{"_column_size":33,"_inline_size":null,"margin":{"unit":"px","top":"0","right":"24","bottom":"0","left":"0","isLinked":false},"padding":{"unit":"px","top":"0","right":"0","bottom":"0","left":"0","isLinked":false},"margin_mobile":{"unit":"px","top":"0","right":"0","bottom":"0","left":"0","isLinked":false}},"elements":[{"id":"5d88367d","settings":{"icon_type":"image","image":{"url":"https:\/\/zakrademos.com\/app-v2\/wp-content\/uploads\/sites\/40\/2019\/10\/4.png","id":174},"caption":"","title":"100% Secure","description":"Lorem ipsum dolor sit amet, cons \nectetur adipisicing elit, sed do eiusmodtempor incididunt ut. ","cta_text":"Read More","service_box_padding":{"unit":"px","top":"50","right":"35","bottom":"50","left":"35","isLinked":false},"service_box_border_width":{"unit":"px","top":"1","right":"1","bottom":"1","left":"1","isLinked":true},"service_box_border_color":"#f8f8f8","image_size":{"unit":"px","size":140,"sizes":[]},"icon_border_border":"","title_color":"#222222","title_typography_typography":"custom","title_typography_font_size":{"unit":"px","size":29,"sizes":[]},"title_typography_font_weight":"900","title_typography_line_height":{"unit":"em","size":0.83,"sizes":[]},"title_margin":{"unit":"px","top":"40","right":"0","bottom":"0","left":"0","isLinked":false},"description_color":"#5e5e5e","description_typography_typography":"custom","description_typography_font_size":{"unit":"px","size":18,"sizes":[]},"description_typography_font_weight":"400","description_typography_line_height":{"unit":"em","size":1.67,"sizes":[]},"description_margin":{"unit":"px","top":"22","right":"0","bottom":"0","left":"0","isLinked":false},"_box_shadow_box_shadow_type":"yes","_box_shadow_box_shadow":{"horizontal":1,"vertical":1.7,"blur":37.2,"spread":2.8,"color":"rgba(34,31,31,0.08)"},"service_box_padding_tablet":{"unit":"px","top":"40","right":"20","bottom":"40","left":"20","isLinked":false},"service_box_bg_background":"classic"},"elements":[],"isInner":false,"widgetType":"elementor-companion-service-box","elType":"widget"}],"isInner":true,"elType":"column"},{"id":"927ec5d","settings":{"_column_size":33,"_inline_size":null,"margin":{"unit":"px","top":"100","right":"12","bottom":"0","left":"12","isLinked":false},"padding":{"unit":"px","top":"0","right":"0","bottom":"0","left":"0","isLinked":false},"margin_mobile":{"unit":"px","top":"30","right":"0","bottom":"0","left":"0","isLinked":false}},"elements":[{"id":"5bafc83d","settings":{"icon_type":"image","image":{"url":"https:\/\/zakrademos.com\/app-v2\/wp-content\/uploads\/sites\/40\/2019\/10\/easy-icon.png","id":177},"caption":"","title":"Easy Setting","description":"Lorem ipsum dolor sit amet, cons \nectetur adipisicing elit, sed do eiusmodtempor incididunt ut. ","cta_text":"Read More","service_box_padding":{"unit":"px","top":"50","right":"35","bottom":"50","left":"35","isLinked":false},"service_box_border_width":{"unit":"px","top":"1","right":"1","bottom":"1","left":"1","isLinked":true},"service_box_border_color":"#f8f8f8","image_size":{"unit":"px","size":140,"sizes":[]},"icon_border_border":"","title_color":"#222222","title_typography_typography":"custom","title_typography_font_size":{"unit":"px","size":29,"sizes":[]},"title_typography_font_weight":"900","title_typography_line_height":{"unit":"em","size":0.83,"sizes":[]},"title_margin":{"unit":"px","top":"40","right":"0","bottom":"0","left":"0","isLinked":false},"description_color":"#5e5e5e","description_typography_typography":"custom","description_typography_font_size":{"unit":"px","size":18,"sizes":[]},"description_typography_font_weight":"400","description_typography_line_height":{"unit":"em","size":1.67,"sizes":[]},"description_margin":{"unit":"px","top":"22","right":"0","bottom":"0","left":"0","isLinked":false},"_box_shadow_box_shadow_type":"yes","_box_shadow_box_shadow":{"horizontal":1,"vertical":1.7,"blur":37.2,"spread":2.8,"color":"rgba(34,31,31,0.08)"},"service_box_padding_tablet":{"unit":"px","top":"40","right":"20","bottom":"40","left":"20","isLinked":false}},"elements":[],"isInner":false,"widgetType":"elementor-companion-service-box","elType":"widget"}],"isInner":true,"elType":"column"},{"id":"2c72a840","settings":{"_column_size":33,"_inline_size":null,"margin":{"unit":"px","top":"0","right":"0","bottom":"0","left":"24","isLinked":false},"padding":{"unit":"px","top":"0","right":"0","bottom":"0","left":"0","isLinked":false},"margin_mobile":{"unit":"px","top":"30","right":"0","bottom":"0","left":"0","isLinked":false}},"elements":[{"id":"369a36d0","settings":{"icon_type":"image","image":{"url":"https:\/\/zakrademos.com\/app-v2\/wp-content\/uploads\/sites\/40\/2019\/10\/5.png","id":173},"caption":"","title":"Fast","description":"Lorem ipsum dolor sit amet, cons \nectetur adipisicing elit, sed do eiusmodtempor incididunt ut. ","cta_text":"Read More","service_box_padding":{"unit":"px","top":"50","right":"35","bottom":"50","left":"35","isLinked":false},"service_box_border_width":{"unit":"px","top":"1","right":"1","bottom":"1","left":"1","isLinked":true},"service_box_border_color":"#f8f8f8","image_size":{"unit":"px","size":140,"sizes":[]},"icon_border_border":"","title_color":"#222222","title_typography_typography":"custom","title_typography_font_size":{"unit":"px","size":29,"sizes":[]},"title_typography_font_weight":"900","title_typography_line_height":{"unit":"em","size":0.83,"sizes":[]},"title_margin":{"unit":"px","top":"40","right":"0","bottom":"0","left":"0","isLinked":false},"description_color":"#5e5e5e","description_typography_typography":"custom","description_typography_font_size":{"unit":"px","size":18,"sizes":[]},"description_typography_font_weight":"400","description_typography_line_height":{"unit":"em","size":1.67,"sizes":[]},"description_margin":{"unit":"px","top":"22","right":"0","bottom":"0","left":"0","isLinked":false},"_box_shadow_box_shadow_type":"yes","_box_shadow_box_shadow":{"horizontal":1,"vertical":1.7,"blur":37.2,"spread":2.8,"color":"rgba(34,31,31,0.08)"},"service_box_padding_tablet":{"unit":"px","top":"40","right":"20","bottom":"40","left":"20","isLinked":false}},"elements":[],"isInner":false,"widgetType":"elementor-companion-service-box","elType":"widget"}],"isInner":true,"elType":"column"}],"isInner":true,"elType":"section"},{"id":"4d5e7bd5","settings":{"layout":"full_width"},"elements":[{"id":"298f3d68","settings":{"_column_size":100,"padding":{"unit":"px","top":"0","right":"0","bottom":"0","left":"0","isLinked":false}},"elements":[{"id":"6681c109","settings":{"space":{"unit":"px","size":220,"sizes":[]},"space_mobile":{"unit":"px","size":110,"sizes":[]},"space_tablet":{"unit":"px","size":140,"sizes":[]}},"elements":[],"isInner":false,"widgetType":"spacer","elType":"widget"}],"isInner":false,"elType":"column"}],"isInner":false,"elType":"section"}],"isInner":false,"elType":"column"}],"isInner":false,"elType":"section"},{"id":"5676a06e","settings":{"structure":"20","background_background":"classic","background_color":"#494dbb","reverse_order_mobile":"reverse-mobile"},"elements":[{"id":"746a0ac9","settings":{"_column_size":50,"_inline_size":null,"margin":{"unit":"px","top":"0","right":"50","bottom":"0","left":"0","isLinked":false},"padding":{"unit":"px","top":"0","right":"0","bottom":"0","left":"0","isLinked":false},"margin_tablet":{"unit":"px","top":"0","right":"35","bottom":"0","left":"0","isLinked":false},"margin_mobile":{"unit":"px","top":"0","right":"15","bottom":"0","left":"15","isLinked":false}},"elements":[{"id":"251a4270","settings":{"image":{"url":"https:\/\/zakrademos.com\/app-v2\/wp-content\/uploads\/sites\/40\/2019\/10\/sign-up.png","id":109},"align":"right","_margin":{"unit":"px","top":"80","right":"0","bottom":"0","left":"0","isLinked":false}},"elements":[],"isInner":false,"widgetType":"image","elType":"widget"}],"isInner":false,"elType":"column"},{"id":"9c2c4ed","settings":{"_column_size":50,"_inline_size":null,"content_position":"center","margin":{"unit":"px","top":"0","right":"0","bottom":"0","left":"30","isLinked":false},"padding":{"unit":"px","top":"0","right":"0","bottom":"0","left":"0","isLinked":false},"margin_tablet":{"unit":"px","top":"0","right":"10","bottom":"0","left":"10","isLinked":false},"margin_mobile":{"unit":"px","top":"60","right":"15","bottom":"0","left":"15","isLinked":false}},"elements":[{"id":"31574502","settings":{"title":"Get The App Now!","align":"left","title_color":"#ffffff","typography_typography":"custom","typography_font_size":{"unit":"px","size":50,"sizes":[]},"typography_font_weight":"700","typography_line_height":{"unit":"em","size":1.4,"sizes":[]},"text_shadow_text_shadow_type":"yes","text_shadow_text_shadow":{"horizontal":0,"vertical":0,"blur":"","color":"rgba(0,0,0,0.3)"},"typography_font_size_tablet":{"unit":"px","size":35,"sizes":[]},"align_mobile":"center"},"elements":[],"isInner":false,"widgetType":"heading","elType":"widget"},{"id":"5f4127a3","settings":{"title":"Lorem ipsum dolor sit amet, consectetur adipisicing elit, sed do eiusmodtempor incididunt ut labore et dolore magna aliqua.","header_size":"p","align":"left","title_color":"#ffffff","typography_typography":"custom","typography_font_size":{"unit":"px","size":16,"sizes":[]},"typography_font_weight":"400","typography_line_height":{"unit":"em","size":1.88,"sizes":[]},"text_shadow_text_shadow_type":"yes","text_shadow_text_shadow":{"horizontal":0,"vertical":0,"blur":"","color":"rgba(0,0,0,0.3)"},"_margin":{"unit":"px","top":"15","right":"0","bottom":"0","left":"0","isLinked":false},"align_mobile":"center"},"elements":[],"isInner":false,"widgetType":"heading","elType":"widget"},{"id":"73f3a02c","settings":{"icon":"fa fa-apple","caption":"","title":"Download Now","description":"App Store","cta_type":"button","cta_text":"","cta_link":{"url":"#","is_external":"on","nofollow":false},"content_alignment":"left","service_box_padding":{"unit":"px","top":"11","right":"30","bottom":"6","left":"30","isLinked":false},"service_box_border_width":{"unit":"px","top":"1","right":"1","bottom":"1","left":"1","isLinked":true},"service_box_border_color":"#ffffff","service_box_border_radius":{"unit":"px","top":"10","right":"10","bottom":"10","left":"10","isLinked":true},"service_box_bg_background":"classic","service_box_bg_color":"#ffffff","service_box_hover_bg_background":"classic","service_box_hover_bg_color":"#f35488","service_box_hover_border_color":"#f35488","service_box_hover_icon_color":"#ffffff","service_box_hover_icon_border_color":"#ffffff","service_box_hover_title_color":"#ffffff","service_box_hover_description_color":"#ffffff","icon_position":"left","icon_vertical_alignment":"center","icon_size":{"unit":"px","size":18,"sizes":[]},"icon_font_size":{"unit":"px","size":37,"sizes":[]},"icon_border_border":"","icon_normal_color":"#222222","title_color":"#222222","title_typography_typography":"custom","title_typography_font_size":{"unit":"px","size":14,"sizes":[]},"title_typography_font_weight":"400","description_color":"#222222","description_typography_typography":"custom","description_typography_font_size":{"unit":"px","size":22,"sizes":[]},"description_typography_font_weight":"900","description_margin":{"unit":"px","top":"-20","right":"0","bottom":"0","left":"0","isLinked":false},"service_box_padding_tablet":{"unit":"px","top":"10","right":"15","bottom":"10","left":"15","isLinked":false},"icon_size_tablet":{"unit":"px","size":4,"sizes":[]},"icon_font_size_tablet":{"unit":"px","size":32,"sizes":[]},"title_typography_font_size_tablet":{"unit":"px","size":12,"sizes":[]},"description_typography_font_size_tablet":{"unit":"px","size":16,"sizes":[]},"description_typography_line_height_tablet":{"unit":"em","size":1.2,"sizes":[]},"description_margin_tablet":{"unit":"px","top":"-6","right":"0","bottom":"0","left":"0","isLinked":false},"icon_size_mobile":{"unit":"px","size":6,"sizes":[]},"icon_font_size_mobile":{"unit":"px","size":30,"sizes":[]},"icon_margin":{"unit":"px","top":"5","right":"0","bottom":"0","left":"0","isLinked":false},"icon_margin_tablet":{"unit":"px","top":"15","right":"0","bottom":"0","left":"0","isLinked":false},"description_typography_font_size_mobile":{"unit":"px","size":15,"sizes":[]},"_margin_mobile":{"unit":"px","top":"0","right":"5","bottom":"0","left":"0","isLinked":false},"_element_width":"auto"},"elements":[],"isInner":false,"widgetType":"elementor-companion-service-box","elType":"widget"},{"id":"2a4b0110","settings":{"icon":"fa fa-android","caption":"","title":"Get It on","description":"Google Play","cta_type":"button","cta_text":"","cta_link":{"url":"#","is_external":"on","nofollow":false},"content_alignment":"left","service_box_padding":{"unit":"px","top":"11","right":"23","bottom":"6","left":"23","isLinked":false},"service_box_border_width":{"unit":"px","top":"1","right":"1","bottom":"1","left":"1","isLinked":true},"service_box_border_color":"#ffffff","service_box_border_radius":{"unit":"px","top":"10","right":"10","bottom":"10","left":"10","isLinked":true},"service_box_bg_background":"classic","service_box_bg_color":"rgba(255,255,255,0)","service_box_hover_bg_background":"classic","service_box_hover_bg_color":"#f35488","service_box_hover_border_color":"#f35488","service_box_hover_icon_color":"#ffffff","service_box_hover_icon_border_color":"#ffffff","service_box_hover_title_color":"#ffffff","service_box_hover_description_color":"#ffffff","icon_position":"left","icon_vertical_alignment":"center","icon_size":{"unit":"px","size":18,"sizes":[]},"icon_font_size":{"unit":"px","size":37,"sizes":[]},"icon_border_border":"","icon_normal_color":"#ffffff","title_color":"#ffffff","title_typography_typography":"custom","title_typography_font_size":{"unit":"px","size":14,"sizes":[]},"title_typography_font_weight":"400","description_color":"#ffffff","description_typography_typography":"custom","description_typography_font_size":{"unit":"px","size":22,"sizes":[]},"description_typography_font_weight":"900","description_margin":{"unit":"px","top":"-20","right":"0","bottom":"0","left":"0","isLinked":false},"service_box_padding_tablet":{"unit":"px","top":"10","right":"15","bottom":"10","left":"15","isLinked":false},"icon_size_tablet":{"unit":"px","size":4,"sizes":[]},"icon_font_size_tablet":{"unit":"px","size":32,"sizes":[]},"title_typography_font_size_tablet":{"unit":"px","size":12,"sizes":[]},"description_typography_font_size_tablet":{"unit":"px","size":16,"sizes":[]},"description_typography_line_height_tablet":{"unit":"em","size":1.2,"sizes":[]},"description_margin_tablet":{"unit":"px","top":"-6","right":"0","bottom":"0","left":"0","isLinked":false},"icon_size_mobile":{"unit":"px","size":6,"sizes":[]},"icon_font_size_mobile":{"unit":"px","size":30,"sizes":[]},"icon_margin":{"unit":"px","top":"5","right":"0","bottom":"0","left":"0","isLinked":false},"icon_margin_tablet":{"unit":"px","top":"15","right":"0","bottom":"0","left":"0","isLinked":false},"_margin":{"unit":"px","top":"0","right":"0","bottom":"0","left":"34","isLinked":false},"_margin_tablet":{"unit":"px","top":"0","right":"0","bottom":"0","left":"15","isLinked":false},"_margin_mobile":{"unit":"px","top":"0","right":"0","bottom":"0","left":"5","isLinked":false},"description_typography_font_size_mobile":{"unit":"px","size":15,"sizes":[]},"_element_width":"auto"},"elements":[],"isInner":false,"widgetType":"elementor-companion-service-box","elType":"widget"}],"isInner":false,"elType":"column"}],"isInner":false,"elType":"section"},{"id":"1ce0165c","settings":{"background_background":"classic","background_image":{"url":"http:\/\/dandelion-camel.w6.wpsandbox.pro\/wp-content\/uploads\/2019\/10\/banner.jpg","id":66},"background_position":"center center","background_attachment":"fixed","background_repeat":"no-repeat","background_size":"cover","background_overlay_background":"classic","background_overlay_color":"#ffffff","background_overlay_opacity":{"unit":"px","size":0.95,"sizes":[]}},"elements":[{"id":"30c48c0f","settings":{"_column_size":100,"padding":{"unit":"px","top":"0","right":"0","bottom":"0","left":"0","isLinked":false}},"elements":[{"id":"45f98f83","settings":{"space":{"unit":"px","size":180,"sizes":[]},"space_mobile":{"unit":"px","size":85,"sizes":[]},"space_tablet":{"unit":"px","size":110,"sizes":[]}},"elements":[],"isInner":false,"widgetType":"spacer","elType":"widget"},{"id":"7c0f7eec","settings":{"structure":"50"},"elements":[{"id":"40fe14c5","settings":{"_column_size":20,"_inline_size":31,"padding":{"unit":"px","top":"0","right":"0","bottom":"0","left":"0","isLinked":false},"_inline_size_tablet":29,"_inline_size_mobile":10},"elements":[{"id":"3ad97ce1","settings":{"divider_type":"normal","text":"I am a Divider","divider_alignment":"right","divider_stacked":"yes","divider_direction":"vertical","icon_position":"left","icon_border_width":{"unit":"px","top":"0","right":"0","bottom":"0","left":"0","isLinked":true},"individual_style":"","divider_color":"#eb3970","divider_length":{"unit":"px","size":66,"sizes":[]},"divider_weight":{"unit":"px","size":2,"sizes":[]},"divider_length_tablet":{"unit":"px","size":45,"sizes":[]}},"elements":[],"isInner":false,"widgetType":"elementor-companion-divider","elType":"widget"}],"isInner":true,"elType":"column"},{"id":"7f50f4c0","settings":{"_column_size":20,"_inline_size":5,"padding":{"unit":"px","top":"0","right":"0","bottom":"0","left":"0","isLinked":false},"_inline_size_tablet":5,"_inline_size_mobile":10},"elements":[{"id":"558ea621","settings":{"divider_type":"normal","text":"I am a Divider","divider_alignment":"left","divider_stacked":"yes","icon_position":"left","icon_border_width":{"unit":"px","top":"0","right":"0","bottom":"0","left":"0","isLinked":true},"individual_style":"","divider_color":"#eb3970","divider_length":{"unit":"px","size":66,"sizes":[]},"divider_length_tablet":{"unit":"px","size":45,"sizes":[]}},"elements":[],"isInner":false,"widgetType":"elementor-companion-divider","elType":"widget"}],"isInner":true,"elType":"column"},{"id":"22973be8","settings":{"_column_size":20,"_inline_size":28,"_inline_size_tablet":32,"_inline_size_mobile":60},"elements":[{"id":"368cf443","settings":{"title":"App Feature","align":"center","title_color":"#eb3970","typography_typography":"custom","typography_font_size":{"unit":"px","size":50,"sizes":[]},"typography_font_weight":"900","text_shadow_text_shadow_type":"yes","text_shadow_text_shadow":{"horizontal":0,"vertical":0,"blur":"","color":"rgba(0,0,0,0.3)"},"_padding":{"unit":"px","top":"15","right":"0","bottom":"15","left":"0","isLinked":false},"typography_font_size_tablet":{"unit":"px","size":38,"sizes":[]},"typography_font_size_mobile":{"unit":"px","size":32,"sizes":[]}},"elements":[],"isInner":false,"widgetType":"heading","elType":"widget"}],"isInner":true,"elType":"column"},{"id":"1e87486f","settings":{"_column_size":20,"_inline_size":5,"content_position":"bottom","border_border":"solid","border_width":{"unit":"px","top":"0","right":"0","bottom":"0","left":"0","isLinked":true},"padding":{"unit":"px","top":"0","right":"0","bottom":"0","left":"0","isLinked":true},"_inline_size_tablet":5,"_inline_size_mobile":10},"elements":[{"id":"22b73102","settings":{"divider_type":"normal","text":"I am a Divider","divider_alignment":"right","divider_stacked":"yes","icon_position":"left","icon_border_width":{"unit":"px","top":"0","right":"0","bottom":"0","left":"0","isLinked":true},"individual_style":"","divider_color":"#eb3970","divider_length":{"unit":"px","size":66,"sizes":[]},"divider_length_tablet":{"unit":"px","size":45,"sizes":[]}},"elements":[],"isInner":false,"widgetType":"elementor-companion-divider","elType":"widget"}],"isInner":true,"elType":"column"},{"id":"67790755","settings":{"_column_size":20,"_inline_size":31,"content_position":"bottom","padding":{"unit":"px","top":"0","right":"0","bottom":"0","left":"0","isLinked":false},"_inline_size_tablet":29,"_inline_size_mobile":10},"elements":[{"id":"4f10e31e","settings":{"divider_type":"normal","text":"I am a Divider","divider_alignment":"left","divider_stacked":"yes","divider_direction":"vertical","icon_position":"left","icon_border_width":{"unit":"px","top":"0","right":"0","bottom":"0","left":"0","isLinked":true},"individual_style":"","divider_color":"#eb3970","divider_length":{"unit":"px","size":66,"sizes":[]},"divider_weight":{"unit":"px","size":2,"sizes":[]},"divider_length_tablet":{"unit":"px","size":45,"sizes":[]}},"elements":[],"isInner":false,"widgetType":"elementor-companion-divider","elType":"widget"}],"isInner":true,"elType":"column"}],"isInner":true,"elType":"section"},{"id":"2e2373f9","settings":{"space":{"unit":"px","size":105,"sizes":[]},"space_tablet":{"unit":"px","size":60,"sizes":[]},"space_mobile":{"unit":"px","size":25,"sizes":[]}},"elements":[],"isInner":false,"widgetType":"spacer","elType":"widget"},{"id":"3d9eeeb8","settings":{"structure":"30","padding_tablet":{"unit":"px","top":"0","right":"15","bottom":"0","left":"15","isLinked":false}},"elements":[{"id":"6f9b77d3","settings":{"_column_size":33,"_inline_size":null,"margin":{"unit":"px","top":"80","right":"20","bottom":"80","left":"0","isLinked":false},"padding":{"unit":"px","top":"0","right":"0","bottom":"0","left":"0","isLinked":false},"margin_tablet":{"unit":"px","top":"0","right":"0","bottom":"0","left":"0","isLinked":true}},"elements":[{"id":"4328cf93","settings":{"icon":"fa fa-dashboard","caption":"","title":"Performance","description":"Lorem ipstum dolor sit amet, cons ectetur adipisicing elit.","cta_text":"Read More","content_alignment":"left","service_box_border_border":"","icon_position":"right","icon_vertical_alignment":"center","icon_size":{"unit":"px","size":90,"sizes":[]},"icon_font_size":{"unit":"px","size":40,"sizes":[]},"icon_border_border":"","icon_border_color":"#f35488","icon_normal_color":"#ffffff","icon_normal_bg_background":"classic","icon_normal_bg_color":"#f35488","title_color":"#f35488","title_typography_typography":"custom","title_typography_font_size":{"unit":"px","size":30,"sizes":[]},"title_typography_font_weight":"700","description_color":"#5e5e5e","description_typography_typography":"custom","description_typography_font_size":{"unit":"px","size":18,"sizes":[]},"description_typography_font_weight":"400","description_typography_line_height":{"unit":"em","size":1.6,"sizes":[]},"_margin":{"unit":"px","top":"40","right":"0","bottom":"0","left":"0","isLinked":false},"icon_size_tablet":{"unit":"px","size":65,"sizes":[]},"icon_font_size_tablet":{"unit":"px","size":30,"sizes":[]},"title_typography_font_size_tablet":{"unit":"px","size":25,"sizes":[]},"description_typography_font_size_tablet":{"unit":"px","size":17,"sizes":[]},"content_alignment_mobile":"center","service_box_padding":{"unit":"px","top":"0","right":"0","bottom":"0","left":"0","isLinked":false},"icon_position_mobile":"top","_margin_tablet":{"unit":"px","top":"0","right":"0","bottom":"0","left":"0","isLinked":false}},"elements":[],"isInner":false,"widgetType":"elementor-companion-service-box","elType":"widget"},{"id":"5376b49","settings":{"icon":"fa fa-briefcase","caption":"","title":"Security","description":"Lorem ipstum dolor sit amet, cons ectetur adipisicing elit.","cta_text":"Read More","content_alignment":"left","service_box_border_border":"","icon_position":"right","icon_vertical_alignment":"center","icon_size":{"unit":"px","size":90,"sizes":[]},"icon_font_size":{"unit":"px","size":40,"sizes":[]},"icon_border_border":"","icon_border_color":"#f35488","icon_normal_color":"#ffffff","icon_normal_bg_background":"classic","icon_normal_bg_color":"#f35488","title_color":"#f35488","title_typography_typography":"custom","title_typography_font_size":{"unit":"px","size":30,"sizes":[]},"title_typography_font_weight":"700","description_color":"#5e5e5e","description_typography_typography":"custom","description_typography_font_size":{"unit":"px","size":18,"sizes":[]},"description_typography_font_weight":"400","description_typography_line_height":{"unit":"em","size":1.6,"sizes":[]},"_margin":{"unit":"px","top":"40","right":"0","bottom":"0","left":"0","isLinked":false},"icon_size_tablet":{"unit":"px","size":65,"sizes":[]},"icon_font_size_tablet":{"unit":"px","size":30,"sizes":[]},"title_typography_font_size_tablet":{"unit":"px","size":25,"sizes":[]},"description_typography_font_size_tablet":{"unit":"px","size":17,"sizes":[]},"content_alignment_mobile":"center","service_box_padding":{"unit":"px","top":"0","right":"0","bottom":"0","left":"0","isLinked":false},"icon_position_mobile":"top","_margin_tablet":{"unit":"px","top":"20","right":"0","bottom":"0","left":"0","isLinked":false},"_margin_mobile":{"unit":"px","top":"30","right":"0","bottom":"0","left":"0","isLinked":false}},"elements":[],"isInner":false,"widgetType":"elementor-companion-service-box","elType":"widget"},{"id":"64bdaac9","settings":{"icon":"fa fa-share-alt","caption":"","title":"Social","description":"Lorem ipstum dolor sit amet, cons ectetur adipisicing elit.","cta_text":"Read More","content_alignment":"left","service_box_border_border":"","icon_position":"right","icon_vertical_alignment":"center","icon_size":{"unit":"px","size":90,"sizes":[]},"icon_font_size":{"unit":"px","size":40,"sizes":[]},"icon_border_border":"","icon_border_color":"#f35488","icon_normal_color":"#ffffff","icon_normal_bg_background":"classic","icon_normal_bg_color":"#f35488","title_color":"#f35488","title_typography_typography":"custom","title_typography_font_size":{"unit":"px","size":30,"sizes":[]},"title_typography_font_weight":"700","description_color":"#5e5e5e","description_typography_typography":"custom","description_typography_font_size":{"unit":"px","size":18,"sizes":[]},"description_typography_font_weight":"400","description_typography_line_height":{"unit":"em","size":1.6,"sizes":[]},"_margin":{"unit":"px","top":"70","right":"0","bottom":"0","left":"0","isLinked":false},"icon_size_tablet":{"unit":"px","size":65,"sizes":[]},"icon_font_size_tablet":{"unit":"px","size":30,"sizes":[]},"title_typography_font_size_tablet":{"unit":"px","size":25,"sizes":[]},"description_typography_font_size_tablet":{"unit":"px","size":17,"sizes":[]},"content_alignment_mobile":"center","service_box_padding":{"unit":"px","top":"0","right":"0","bottom":"0","left":"0","isLinked":false},"icon_position_mobile":"top","_margin_tablet":{"unit":"px","top":"20","right":"0","bottom":"0","left":"0","isLinked":false},"_margin_mobile":{"unit":"px","top":"30","right":"0","bottom":"0","left":"0","isLinked":false}},"elements":[],"isInner":false,"widgetType":"elementor-companion-service-box","elType":"widget"}],"isInner":true,"elType":"column"},{"id":"4b3f6bd3","settings":{"_column_size":33,"_inline_size":null,"padding":{"unit":"px","top":"0","right":"0","bottom":"0","left":"0","isLinked":false},"content_position_tablet":"center","margin_mobile":{"unit":"px","top":"70","right":"0","bottom":"0","left":"0","isLinked":false},"padding_tablet":{"unit":"px","top":"0","right":"15","bottom":"0","left":"15","isLinked":false},"padding_mobile":{"unit":"px","top":"0","right":"0","bottom":"0","left":"0","isLinked":false}},"elements":[{"id":"4b263072","settings":{"image":{"url":"https:\/\/zakrademos.com\/app-v2\/wp-content\/uploads\/sites\/40\/2019\/10\/app-feature.png","id":113},"image_size":"medium_large","width_mobile":{"unit":"%","size":70,"sizes":[]}},"elements":[],"isInner":false,"widgetType":"image","elType":"widget"}],"isInner":true,"elType":"column"},{"id":"7f6d470d","settings":{"_column_size":33,"_inline_size":null,"margin":{"unit":"px","top":"80","right":"0","bottom":"80","left":"20","isLinked":false},"padding":{"unit":"px","top":"0","right":"0","bottom":"0","left":"0","isLinked":false},"margin_tablet":{"unit":"px","top":"0","right":"0","bottom":"0","left":"0","isLinked":true},"margin_mobile":{"unit":"px","top":"80","right":"0","bottom":"0","left":"0","isLinked":false}},"elements":[{"id":"192ab53c","settings":{"icon":"fa fa-bar-chart-o","caption":"","title":"Analytics","description":"Lorem ipstum dolor sit amet, cons ectetur adipisicing elit.","cta_text":"Read More","content_alignment":"left","service_box_border_border":"","icon_position":"left","icon_vertical_alignment":"center","icon_size":{"unit":"px","size":90,"sizes":[]},"icon_font_size":{"unit":"px","size":40,"sizes":[]},"icon_border_border":"","icon_border_color":"#f35488","icon_normal_color":"#ffffff","icon_normal_bg_background":"classic","icon_normal_bg_color":"#f35488","title_color":"#f35488","title_typography_typography":"custom","title_typography_font_size":{"unit":"px","size":30,"sizes":[]},"title_typography_font_weight":"700","description_color":"#5e5e5e","description_typography_typography":"custom","description_typography_font_size":{"unit":"px","size":18,"sizes":[]},"description_typography_font_weight":"400","description_typography_line_height":{"unit":"em","size":1.6,"sizes":[]},"service_box_padding":{"unit":"px","top":"0","right":"0","bottom":"0","left":"0","isLinked":true},"_margin":{"unit":"px","top":"40","right":"0","bottom":"0","left":"0","isLinked":false},"content_alignment_mobile":"center","icon_position_mobile":"top","icon_size_tablet":{"unit":"px","size":65,"sizes":[]},"icon_font_size_tablet":{"unit":"px","size":30,"sizes":[]},"title_typography_font_size_tablet":{"unit":"px","size":25,"sizes":[]},"description_typography_font_size_tablet":{"unit":"px","size":17,"sizes":[]},"_margin_tablet":{"unit":"px","top":"0","right":"0","bottom":"0","left":"0","isLinked":false}},"elements":[],"isInner":false,"widgetType":"elementor-companion-service-box","elType":"widget"},{"id":"1884ac48","settings":{"icon":"fa fa-mobile-phone","caption":"","title":"Android","description":"Lorem ipstum dolor sit amet, cons ectetur adipisicing elit.","cta_text":"Read More","content_alignment":"left","service_box_border_border":"","icon_position":"left","icon_vertical_alignment":"center","icon_size":{"unit":"px","size":90,"sizes":[]},"icon_font_size":{"unit":"px","size":40,"sizes":[]},"icon_border_border":"","icon_border_color":"#f35488","icon_normal_color":"#ffffff","icon_normal_bg_background":"classic","icon_normal_bg_color":"#f35488","title_color":"#f35488","title_typography_typography":"custom","title_typography_font_size":{"unit":"px","size":30,"sizes":[]},"title_typography_font_weight":"700","description_color":"#5e5e5e","description_typography_typography":"custom","description_typography_font_size":{"unit":"px","size":18,"sizes":[]},"description_typography_font_weight":"400","description_typography_line_height":{"unit":"em","size":1.6,"sizes":[]},"service_box_padding":{"unit":"px","top":"0","right":"0","bottom":"0","left":"0","isLinked":true},"_margin":{"unit":"px","top":"70","right":"0","bottom":"0","left":"0","isLinked":false},"content_alignment_mobile":"center","icon_position_mobile":"top","icon_size_tablet":{"unit":"px","size":65,"sizes":[]},"icon_font_size_tablet":{"unit":"px","size":30,"sizes":[]},"title_typography_font_size_tablet":{"unit":"px","size":25,"sizes":[]},"description_typography_font_size_tablet":{"unit":"px","size":17,"sizes":[]},"_margin_tablet":{"unit":"px","top":"20","right":"0","bottom":"0","left":"0","isLinked":false},"_margin_mobile":{"unit":"px","top":"30","right":"0","bottom":"0","left":"0","isLinked":false}},"elements":[],"isInner":false,"widgetType":"elementor-companion-service-box","elType":"widget"},{"id":"298dad0b","settings":{"icon":"fa fa-support","caption":"","title":"Support","description":"Lorem ipstum dolor sit amet, cons ectetur adipisicing elit.","cta_text":"Read More","content_alignment":"left","service_box_border_border":"","icon_position":"left","icon_vertical_alignment":"center","icon_size":{"unit":"px","size":90,"sizes":[]},"icon_font_size":{"unit":"px","size":40,"sizes":[]},"icon_border_border":"","icon_border_color":"#f35488","icon_normal_color":"#ffffff","icon_normal_bg_background":"classic","icon_normal_bg_color":"#f35488","title_color":"#f35488","title_typography_typography":"custom","title_typography_font_size":{"unit":"px","size":30,"sizes":[]},"title_typography_font_weight":"700","description_color":"#5e5e5e","description_typography_typography":"custom","description_typography_font_size":{"unit":"px","size":18,"sizes":[]},"description_typography_font_weight":"400","description_typography_line_height":{"unit":"em","size":1.6,"sizes":[]},"service_box_padding":{"unit":"px","top":"0","right":"0","bottom":"0","left":"0","isLinked":true},"_margin":{"unit":"px","top":"70","right":"0","bottom":"0","left":"0","isLinked":false},"content_alignment_mobile":"center","icon_position_mobile":"top","icon_size_tablet":{"unit":"px","size":65,"sizes":[]},"icon_font_size_tablet":{"unit":"px","size":30,"sizes":[]},"title_typography_font_size_tablet":{"unit":"px","size":25,"sizes":[]},"description_typography_font_size_tablet":{"unit":"px","size":17,"sizes":[]},"_margin_tablet":{"unit":"px","top":"20","right":"0","bottom":"0","left":"0","isLinked":false},"_margin_mobile":{"unit":"px","top":"30","right":"0","bottom":"0","left":"0","isLinked":false}},"elements":[],"isInner":false,"widgetType":"elementor-companion-service-box","elType":"widget"}],"isInner":true,"elType":"column"}],"isInner":true,"elType":"section"},{"id":"1df7b7d4","settings":{"space":{"unit":"px","size":175,"sizes":[]},"space_mobile":{"unit":"px","size":90,"sizes":[]},"space_tablet":{"unit":"px","size":110,"sizes":[]}},"elements":[],"isInner":false,"widgetType":"spacer","elType":"widget"}],"isInner":false,"elType":"column"}],"isInner":false,"elType":"section"},{"id":"7b21008f","settings":{"background_background":"classic","background_color":"#f35488"},"elements":[{"id":"7fbb341c","settings":{"_column_size":100,"margin":{"unit":"px","top":"0","right":"0","bottom":"-210","left":"0","isLinked":false},"padding_tablet":{"unit":"px","top":"0","right":"15","bottom":"0","left":"15","isLinked":false}},"elements":[{"id":"11eb5800","settings":{"space":{"unit":"px","size":170,"sizes":[]},"space_mobile":{"unit":"px","size":90,"sizes":[]},"space_tablet":{"unit":"px","size":110,"sizes":[]}},"elements":[],"isInner":false,"widgetType":"spacer","elType":"widget"},{"id":"3847ded","settings":{"structure":"50"},"elements":[{"id":"26a2db49","settings":{"_column_size":20,"_inline_size":31,"padding":{"unit":"px","top":"0","right":"0","bottom":"0","left":"0","isLinked":false},"_inline_size_tablet":28,"_inline_size_mobile":5},"elements":[{"id":"5b0f8d20","settings":{"divider_type":"normal","text":"I am a Divider","divider_alignment":"right","divider_stacked":"yes","divider_direction":"vertical","icon_position":"left","icon_border_width":{"unit":"px","top":"0","right":"0","bottom":"0","left":"0","isLinked":true},"individual_style":"","divider_color":"#ffffff","divider_length":{"unit":"px","size":66,"sizes":[]},"divider_weight":{"unit":"px","size":2,"sizes":[]},"divider_length_tablet":{"unit":"px","size":45,"sizes":[]}},"elements":[],"isInner":false,"widgetType":"elementor-companion-divider","elType":"widget"}],"isInner":true,"elType":"column"},{"id":"21091ca3","settings":{"_column_size":20,"_inline_size":3,"padding":{"unit":"px","top":"0","right":"0","bottom":"0","left":"0","isLinked":false},"_inline_size_tablet":6,"_inline_size_mobile":9},"elements":[{"id":"6861f86e","settings":{"divider_type":"normal","text":"I am a Divider","divider_alignment":"left","divider_stacked":"yes","icon_position":"left","icon_border_width":{"unit":"px","top":"0","right":"0","bottom":"0","left":"0","isLinked":true},"individual_style":"","divider_color":"#ffffff","divider_length":{"unit":"px","size":66,"sizes":[]},"divider_length_tablet":{"unit":"px","size":45,"sizes":[]}},"elements":[],"isInner":false,"widgetType":"elementor-companion-divider","elType":"widget"}],"isInner":true,"elType":"column"},{"id":"29600d33","settings":{"_column_size":20,"_inline_size":32,"_inline_size_mobile":72},"elements":[{"id":"617c582a","settings":{"title":"Testimonials","align":"center","title_color":"#ffffff","typography_typography":"custom","typography_font_size":{"unit":"px","size":50,"sizes":[]},"typography_font_weight":"900","text_shadow_text_shadow_type":"yes","text_shadow_text_shadow":{"horizontal":0,"vertical":0,"blur":"","color":"rgba(0,0,0,0.3)"},"_padding":{"unit":"px","top":"15","right":"0","bottom":"15","left":"0","isLinked":false},"typography_font_size_tablet":{"unit":"px","size":38,"sizes":[]},"typography_font_size_mobile":{"unit":"px","size":32,"sizes":[]}},"elements":[],"isInner":false,"widgetType":"heading","elType":"widget"}],"isInner":true,"elType":"column"},{"id":"60cd4cea","settings":{"_column_size":20,"_inline_size":3,"content_position":"bottom","border_border":"solid","border_width":{"unit":"px","top":"0","right":"0","bottom":"0","left":"0","isLinked":true},"padding":{"unit":"px","top":"0","right":"0","bottom":"0","left":"0","isLinked":true},"_inline_size_tablet":6,"_inline_size_mobile":9},"elements":[{"id":"7697c2c5","settings":{"divider_type":"normal","text":"I am a Divider","divider_alignment":"right","divider_stacked":"yes","icon_position":"left","icon_border_width":{"unit":"px","top":"0","right":"0","bottom":"0","left":"0","isLinked":true},"individual_style":"","divider_color":"#ffffff","divider_length":{"unit":"px","size":66,"sizes":[]},"divider_length_tablet":{"unit":"px","size":45,"sizes":[]}},"elements":[],"isInner":false,"widgetType":"elementor-companion-divider","elType":"widget"}],"isInner":true,"elType":"column"},{"id":"192efead","settings":{"_column_size":20,"_inline_size":31,"content_position":"bottom","padding":{"unit":"px","top":"0","right":"0","bottom":"0","left":"0","isLinked":false},"_inline_size_tablet":28,"_inline_size_mobile":5},"elements":[{"id":"5fed0177","settings":{"divider_type":"normal","text":"I am a Divider","divider_alignment":"left","divider_stacked":"yes","divider_direction":"vertical","icon_position":"left","icon_border_width":{"unit":"px","top":"0","right":"0","bottom":"0","left":"0","isLinked":true},"individual_style":"","divider_color":"#ffffff","divider_length":{"unit":"px","size":66,"sizes":[]},"divider_weight":{"unit":"px","size":2,"sizes":[]},"divider_length_tablet":{"unit":"px","size":45,"sizes":[]}},"elements":[],"isInner":false,"widgetType":"elementor-companion-divider","elType":"widget"}],"isInner":true,"elType":"column"}],"isInner":true,"elType":"section"},{"id":"7e7449e6","settings":{"space":{"unit":"px","size":100,"sizes":[]},"space_mobile":{"unit":"px","size":45,"sizes":[]},"space_tablet":{"unit":"px","size":60,"sizes":[]}},"elements":[],"isInner":false,"widgetType":"spacer","elType":"widget"},{"id":"2e2654d5","settings":{"structure":"20"},"elements":[{"id":"6afd8542","settings":{"_column_size":50,"_inline_size":35,"padding":{"unit":"px","top":"0","right":"0","bottom":"0","left":"0","isLinked":false}},"elements":[{"id":"683fe1cc","settings":{"title":"We're as good as they say we are","align":"left","title_color":"#ffffff","typography_typography":"custom","typography_font_size":{"unit":"px","size":47,"sizes":[]},"typography_font_weight":"900","typography_line_height":{"unit":"em","size":1.05,"sizes":[]},"text_shadow_text_shadow_type":"yes","text_shadow_text_shadow":{"horizontal":0,"vertical":0,"blur":"","color":"rgba(0,0,0,0.3)"},"align_mobile":"center","typography_font_size_tablet":{"unit":"px","size":45,"sizes":[]},"typography_font_size_mobile":{"unit":"px","size":26,"sizes":[]},"_padding_mobile":{"unit":"px","top":"0","right":"25","bottom":"0","left":"25","isLinked":false}},"elements":[],"isInner":false,"widgetType":"heading","elType":"widget"}],"isInner":true,"elType":"column"},{"id":"166355c5","settings":{"_column_size":50,"_inline_size":65,"margin":{"unit":"px","top":"0","right":"0","bottom":"0","left":"0","isLinked":true},"padding":{"unit":"px","top":"0","right":"30","bottom":"0","left":"30","isLinked":false},"z_index":999,"_inline_size_mobile":100,"margin_mobile":{"unit":"px","top":"50","right":"0","bottom":"0","left":"0","isLinked":false},"padding_mobile":{"unit":"px","top":"0","right":"0","bottom":"0","left":"0","isLinked":false},"background_background":"classic","box_shadow_box_shadow_type":"yes","box_shadow_box_shadow":{"horizontal":0,"vertical":0,"blur":"","spread":0,"color":"rgba(0,0,0,0.5)"}},"elements":[{"id":"7a83c8d3","settings":{"slides":[{"author_name":"Sama Smith","author_caption":"CEO","_id":"b86a64a","author_message":"Lorem Ipsum is simply dummy text of the printing and typesetting industry. Lorem Ipsum has been the industry's standard dummy text ever since the 1500s, when an unknown printer took a galley of type and scrambled it to make a type specimen book. It has survived not only five centuries, but also the leap into electronic typesetting, remaining essentially unchanged. It was popularised in the 1960s passages.","author_image":{"url":"https:\/\/zakrademos.com\/app-v2\/wp-content\/uploads\/sites\/40\/2019\/10\/testimonial.jpg","id":119},"custom_style":"yes","current_slide_bg_background":"","current_slide_bg_color":"","current_slide_bg_color_stop":{"unit":"%","size":0,"sizes":[]},"current_slide_bg_color_b":"#f2295b","current_slide_bg_color_b_stop":{"unit":"%","size":100,"sizes":[]},"current_slide_bg_gradient_type":"linear","current_slide_bg_gradient_angle":{"unit":"deg","size":180,"sizes":[]},"current_slide_bg_gradient_position":"center center","current_slide_bg_image":{"url":"","id":""},"current_slide_bg_image_tablet":{"url":"","id":""},"current_slide_bg_image_mobile":{"url":"","id":""},"current_slide_bg_position":"","current_slide_bg_position_tablet":"","current_slide_bg_position_mobile":"","current_slide_bg_xpos":{"unit":"px","size":0,"sizes":[]},"current_slide_bg_xpos_tablet":{"unit":"px","size":0,"sizes":[]},"current_slide_bg_xpos_mobile":{"unit":"px","size":0,"sizes":[]},"current_slide_bg_ypos":{"unit":"px","size":0,"sizes":[]},"current_slide_bg_ypos_tablet":{"unit":"px","size":0,"sizes":[]},"current_slide_bg_ypos_mobile":{"unit":"px","size":0,"sizes":[]},"current_slide_bg_attachment":"","current_slide_bg_repeat":"","current_slide_bg_repeat_tablet":"","current_slide_bg_repeat_mobile":"","current_slide_bg_size":"","current_slide_bg_size_tablet":"","current_slide_bg_size_mobile":"","current_slide_bg_bg_width":{"unit":"%","size":100,"sizes":[]},"current_slide_bg_bg_width_tablet":{"unit":"px","size":"","sizes":[]},"current_slide_bg_bg_width_mobile":{"unit":"px","size":"","sizes":[]},"current_slide_bg_video_link":"","current_slide_bg_video_start":"","current_slide_bg_video_end":"","current_slide_bg_play_once":"","current_slide_bg_play_on_mobile":"","current_slide_bg_video_fallback":{"url":"","id":""},"current_slide_bg_slideshow_gallery":[],"current_slide_bg_slideshow_loop":"yes","current_slide_bg_slideshow_slide_duration":5000,"current_slide_bg_slideshow_slide_transition":"fade","current_slide_bg_slideshow_transition_duration":500,"current_slide_bg_slideshow_ken_burns":"","current_slide_bg_slideshow_ken_burns_zoom_direction":"in","current_author_name_color":"#f35488","current_author_caption_color":"#5e5e5e","current_author_message_color":"#5e5e5e"},{"author_name":"Jay Jay","author_caption":"Co-Founder","_id":"ea3c3a2","author_message":"Lorem Ipsum is simply dummy text of the printing and typesetting industry. Lorem Ipsum has been the industry's standard dummy text ever since the 1500s, when an unknown printer took a galley of type and scrambled it to make a type specimen book. It has survived not only five centuries, but also the leap into electronic typesetting, remaining essentially unchanged. It was popularised in the 1960s passages.","author_image":{"url":"https:\/\/zakrademos.com\/app-v2\/wp-content\/uploads\/sites\/40\/2019\/11\/testimonial-2.jpg","id":294},"custom_style":"yes","current_slide_bg_background":"","current_slide_bg_color":"","current_slide_bg_color_stop":{"unit":"%","size":0,"sizes":[]},"current_slide_bg_color_b":"#f2295b","current_slide_bg_color_b_stop":{"unit":"%","size":100,"sizes":[]},"current_slide_bg_gradient_type":"linear","current_slide_bg_gradient_angle":{"unit":"deg","size":180,"sizes":[]},"current_slide_bg_gradient_position":"center center","current_slide_bg_image":{"url":"","id":""},"current_slide_bg_image_tablet":{"url":"","id":""},"current_slide_bg_image_mobile":{"url":"","id":""},"current_slide_bg_position":"","current_slide_bg_position_tablet":"","current_slide_bg_position_mobile":"","current_slide_bg_xpos":{"unit":"px","size":0,"sizes":[]},"current_slide_bg_xpos_tablet":{"unit":"px","size":0,"sizes":[]},"current_slide_bg_xpos_mobile":{"unit":"px","size":0,"sizes":[]},"current_slide_bg_ypos":{"unit":"px","size":0,"sizes":[]},"current_slide_bg_ypos_tablet":{"unit":"px","size":0,"sizes":[]},"current_slide_bg_ypos_mobile":{"unit":"px","size":0,"sizes":[]},"current_slide_bg_attachment":"","current_slide_bg_repeat":"","current_slide_bg_repeat_tablet":"","current_slide_bg_repeat_mobile":"","current_slide_bg_size":"","current_slide_bg_size_tablet":"","current_slide_bg_size_mobile":"","current_slide_bg_bg_width":{"unit":"%","size":100,"sizes":[]},"current_slide_bg_bg_width_tablet":{"unit":"px","size":"","sizes":[]},"current_slide_bg_bg_width_mobile":{"unit":"px","size":"","sizes":[]},"current_slide_bg_video_link":"","current_slide_bg_video_start":"","current_slide_bg_video_end":"","current_slide_bg_play_once":"","current_slide_bg_play_on_mobile":"","current_slide_bg_video_fallback":{"url":"","id":""},"current_slide_bg_slideshow_gallery":[],"current_slide_bg_slideshow_loop":"yes","current_slide_bg_slideshow_slide_duration":5000,"current_slide_bg_slideshow_slide_transition":"fade","current_slide_bg_slideshow_transition_duration":500,"current_slide_bg_slideshow_ken_burns":"","current_slide_bg_slideshow_ken_burns_zoom_direction":"in","current_author_name_color":"#f35488","current_author_caption_color":"#5e5e5e","current_author_message_color":"#5e5e5e"}],"spv":"1","autoplay":"","navigation":"arrows","slide_alignment":"left","imageinfo_infobox_position":"down","imageinfo_image_position":"left","slide_bg_background":"classic","slide_bg_color":"#ffffff","slide_padding":{"unit":"px","top":"100","right":"80","bottom":"100","left":"80","isLinked":false},"slide_border_radius":{"unit":"px","top":"35","right":"35","bottom":"35","left":"35","isLinked":true},"image_size":{"unit":"px","size":90,"sizes":[]},"author_image_border_border":"solid","author_image_border_width":{"unit":"px","top":"5","right":"5","bottom":"5","left":"5","isLinked":true},"author_image_border_color":"#f35488","author_image_border_radius":{"unit":"px","top":"49","right":"49","bottom":"49","left":"49","isLinked":true},"author_message_color":"#5e5e5e","author_message_typography_typography":"custom","author_message_typography_font_size":{"unit":"px","size":18,"sizes":[]},"author_message_typography_font_weight":"400","author_message_typography_line_height":{"unit":"em","size":1.67,"sizes":[]},"arrow_border_border":"solid","arrow_border_width":{"unit":"px","top":"1","right":"1","bottom":"1","left":"1","isLinked":true},"arrow_border_color":"rgba(243,84,136,0.05)","arrow_border_radius":{"unit":"px","top":"30","right":"30","bottom":"30","left":"30","isLinked":true},"arrow_box_shadow_box_shadow_type":"yes","arrow_box_shadow_box_shadow":{"horizontal":0,"vertical":0,"blur":"","spread":0,"color":"rgba(0,0,0,0.5)"},"arrow_normal_color":"#f35488","arrow_normal_bg_background":"classic","arrow_normal_bg_color":"rgba(243,84,136,0.21)","slide_box_shadow_box_shadow_type":"yes","slide_box_shadow_box_shadow":{"horizontal":"","vertical":"","blur":"","spread":"","color":"rgba(0,0,0,0.02)"},"arrow_hover_color":"#494dbb","arrow_hover_bg_background":"classic","arrow_hover_bg_color":"rgba(73,77,187,0.33)","_box_shadow_box_shadow_type":"yes","_box_shadow_box_shadow":{"horizontal":"","vertical":"","blur":"","spread":"","color":"rgba(34,31,31,0)"},"spv_tablet":"1","slide_padding_tablet":{"unit":"px","top":"60","right":"60","bottom":"60","left":"60","isLinked":false},"author_caption_typography_typography":"custom","author_message_typography_font_size_mobile":{"unit":"px","size":16,"sizes":[]},"_background_background":"classic","slide_border_color":"rgba(233,236,239,0.35)"},"elements":[],"isInner":false,"widgetType":"elementor-companion-testimonial-carousel","elType":"widget"}],"isInner":true,"elType":"column"}],"isInner":true,"elType":"section"}],"isInner":false,"elType":"column"}],"isInner":false,"elType":"section"},{"id":"59cec18a","settings":[],"elements":[{"id":"31932ee4","settings":{"_column_size":100,"padding":{"unit":"px","top":"0","right":"0","bottom":"0","left":"0","isLinked":false}},"elements":[{"id":"1dc1cca9","settings":{"space":{"unit":"px","size":380,"sizes":[]},"space_mobile":{"unit":"px","size":300,"sizes":[]},"space_tablet":{"unit":"px","size":315,"sizes":[]}},"elements":[],"isInner":false,"widgetType":"spacer","elType":"widget"},{"id":"1fd12942","settings":{"structure":"50"},"elements":[{"id":"46606c62","settings":{"_column_size":20,"_inline_size":34.988,"padding":{"unit":"px","top":"0","right":"0","bottom":"0","left":"0","isLinked":false},"_inline_size_mobile":18},"elements":[{"id":"4ae1648f","settings":{"divider_type":"normal","text":"I am a Divider","divider_alignment":"right","divider_stacked":"yes","divider_direction":"vertical","icon_position":"left","icon_border_width":{"unit":"px","top":"0","right":"0","bottom":"0","left":"0","isLinked":true},"individual_style":"","divider_color":"#eb3970","divider_length":{"unit":"px","size":66,"sizes":[]},"divider_weight":{"unit":"px","size":2,"sizes":[]},"divider_length_tablet":{"unit":"px","size":45,"sizes":[]}},"elements":[],"isInner":false,"widgetType":"elementor-companion-divider","elType":"widget"}],"isInner":true,"elType":"column"},{"id":"636610d7","settings":{"_column_size":20,"_inline_size":4.766,"padding":{"unit":"px","top":"0","right":"0","bottom":"0","left":"0","isLinked":false},"_inline_size_mobile":15},"elements":[{"id":"36ec81e5","settings":{"divider_type":"normal","text":"I am a Divider","divider_alignment":"left","divider_stacked":"yes","icon_position":"left","icon_border_width":{"unit":"px","top":"0","right":"0","bottom":"0","left":"0","isLinked":true},"individual_style":"","divider_color":"#eb3970","divider_length":{"unit":"px","size":66,"sizes":[]},"divider_length_tablet":{"unit":"px","size":45,"sizes":[]}},"elements":[],"isInner":false,"widgetType":"elementor-companion-divider","elType":"widget"}],"isInner":true,"elType":"column"},{"id":"3659c8f2","settings":{"_column_size":20,"_inline_size":20.399,"_inline_size_mobile":34},"elements":[{"id":"6fee196d","settings":{"title":"Videos","align":"center","title_color":"#eb3970","typography_typography":"custom","typography_font_size":{"unit":"px","size":50,"sizes":[]},"typography_font_weight":"900","text_shadow_text_shadow_type":"yes","text_shadow_text_shadow":{"horizontal":0,"vertical":0,"blur":"","color":"rgba(0,0,0,0.3)"},"_padding":{"unit":"px","top":"15","right":"0","bottom":"15","left":"0","isLinked":false},"typography_font_size_tablet":{"unit":"px","size":38,"sizes":[]},"typography_font_size_mobile":{"unit":"px","size":32,"sizes":[]}},"elements":[],"isInner":false,"widgetType":"heading","elType":"widget"}],"isInner":true,"elType":"column"},{"id":"de5d141","settings":{"_column_size":20,"_inline_size":4.862,"content_position":"bottom","border_border":"solid","border_width":{"unit":"px","top":"0","right":"0","bottom":"0","left":"0","isLinked":true},"padding":{"unit":"px","top":"0","right":"0","bottom":"0","left":"0","isLinked":true},"_inline_size_mobile":15},"elements":[{"id":"2104ff8f","settings":{"divider_type":"normal","text":"I am a Divider","divider_alignment":"right","divider_stacked":"yes","icon_position":"left","icon_border_width":{"unit":"px","top":"0","right":"0","bottom":"0","left":"0","isLinked":true},"individual_style":"","divider_color":"#eb3970","divider_length":{"unit":"px","size":66,"sizes":[]},"divider_length_tablet":{"unit":"px","size":45,"sizes":[]}},"elements":[],"isInner":false,"widgetType":"elementor-companion-divider","elType":"widget"}],"isInner":true,"elType":"column"},{"id":"3de515eb","settings":{"_column_size":20,"_inline_size":34.985,"content_position":"bottom","padding":{"unit":"px","top":"0","right":"0","bottom":"0","left":"0","isLinked":false},"_inline_size_mobile":18},"elements":[{"id":"671e5501","settings":{"divider_type":"normal","text":"I am a Divider","divider_alignment":"left","divider_stacked":"yes","divider_direction":"vertical","icon_position":"left","icon_border_width":{"unit":"px","top":"0","right":"0","bottom":"0","left":"0","isLinked":true},"individual_style":"","divider_color":"#eb3970","divider_length":{"unit":"px","size":66,"sizes":[]},"divider_weight":{"unit":"px","size":2,"sizes":[]},"divider_length_tablet":{"unit":"px","size":45,"sizes":[]}},"elements":[],"isInner":false,"widgetType":"elementor-companion-divider","elType":"widget"}],"isInner":true,"elType":"column"}],"isInner":true,"elType":"section"},{"id":"422de221","settings":{"space":{"unit":"px","size":100,"sizes":[]},"space_mobile":{"unit":"px","size":40,"sizes":[]},"space_tablet":{"unit":"px","size":60,"sizes":[]}},"elements":[],"isInner":false,"widgetType":"spacer","elType":"widget"},{"id":"4604495f","settings":{"padding_tablet":{"unit":"px","top":"0","right":"15","bottom":"0","left":"15","isLinked":false}},"elements":[{"id":"6336fec5","settings":{"_column_size":100,"_inline_size":null,"padding":{"unit":"px","top":"0","right":"0","bottom":"0","left":"0","isLinked":false},"box_shadow_box_shadow_type":"yes","box_shadow_box_shadow":{"horizontal":0,"vertical":0,"blur":"","spread":0,"color":"rgba(0,0,0,0.5)"}},"elements":[{"id":"6487f135","settings":{"youtube_url":"https:\/\/www.youtube.com\/watch?v=mO6Ua_FjnoI","vimeo_url":"https:\/\/vimeo.com\/235215203","dailymotion_url":"https:\/\/www.dailymotion.com\/video\/x6tqhqb","show_image_overlay":"yes","image_overlay":{"url":"https:\/\/zakrademos.com\/app-v2\/wp-content\/uploads\/sites\/40\/2019\/10\/video.jpg","id":120},"lightbox":"yes","css_filters_css_filter":"custom","play_icon_color":"#ffffff","play_icon_size":{"unit":"px","size":60,"sizes":[]},"_border_border":"solid","_border_width":{"unit":"px","top":"60","right":"60","bottom":"60","left":"60","isLinked":true},"_border_color":"#ffffff","_box_shadow_box_shadow_type":"yes","_box_shadow_box_shadow":{"horizontal":1,"vertical":1.7,"blur":37.2,"spread":2.8,"color":"rgba(34,31,31,0.08)"},"_border_width_mobile":{"unit":"px","top":"15","right":"15","bottom":"15","left":"15","isLinked":true}},"elements":[],"isInner":false,"widgetType":"video","elType":"widget"},{"id":"83321b0","settings":{"space":{"unit":"px","size":200,"sizes":[]},"space_mobile":{"unit":"px","size":80,"sizes":[]},"space_tablet":{"unit":"px","size":120,"sizes":[]}},"elements":[],"isInner":false,"widgetType":"spacer","elType":"widget"}],"isInner":true,"elType":"column"}],"isInner":true,"elType":"section"}],"isInner":false,"elType":"column"}],"isInner":false,"elType":"section"},{"id":"4379ee4f","settings":{"margin":{"unit":"px","top":"0","right":0,"bottom":"0","left":0,"isLinked":false},"box_shadow_box_shadow_type":"yes","box_shadow_box_shadow":{"horizontal":0,"vertical":0,"blur":"","spread":0,"color":"rgba(0,0,0,0.5)"}},"elements":[{"id":"71a0f7c9","settings":{"_column_size":100,"_inline_size":null,"border_width":{"unit":"px","top":"1","right":"1","bottom":"1","left":"1","isLinked":true},"border_radius":{"unit":"px","top":"25","right":"25","bottom":"25","left":"25","isLinked":true},"box_shadow_box_shadow_type":"yes","box_shadow_box_shadow":{"horizontal":1,"vertical":1.7,"blur":37.2,"spread":2.8,"color":"rgba(34,31,31,0.08)"},"background_background":"classic","background_color":"#ffffff","margin":{"unit":"px","top":"0","right":"0","bottom":"-150","left":"0","isLinked":false},"z_index":999,"margin_tablet":{"unit":"px","top":"0","right":"15","bottom":"-150","left":"15","isLinked":false}},"elements":[{"id":"26d1964a","settings":{"title":"Subscribe to our newsletter","align":"center","title_color":"#222222","typography_typography":"custom","typography_font_size":{"unit":"px","size":40,"sizes":[]},"typography_font_weight":"900","typography_line_height":{"unit":"em","size":1.5,"sizes":[]},"text_shadow_text_shadow_type":"yes","text_shadow_text_shadow":{"horizontal":0,"vertical":0,"blur":"","color":"rgba(0,0,0,0.3)"},"_margin":{"unit":"px","top":"45","right":"0","bottom":"0","left":"0","isLinked":false},"typography_font_size_mobile":{"unit":"px","size":22,"sizes":[]}},"elements":[],"isInner":false,"widgetType":"heading","elType":"widget"},{"id":"1180305b","settings":{"title":"Lorem ipsum dolor sit amet, consectetur adipisicing elit.","header_size":"p","align":"center","title_color":"#5e5e5e","typography_typography":"custom","typography_font_size":{"unit":"px","size":20,"sizes":[]},"typography_font_weight":"400","typography_line_height":{"unit":"em","size":1.2,"sizes":[]},"text_shadow_text_shadow_type":"yes","text_shadow_text_shadow":{"horizontal":0,"vertical":0,"blur":"","color":"rgba(0,0,0,0.3)"},"_margin":{"unit":"px","top":"-10","right":"0","bottom":"0","left":"0","isLinked":false},"typography_font_size_mobile":{"unit":"px","size":16,"sizes":[]}},"elements":[],"isInner":false,"widgetType":"heading","elType":"widget"},{"id":"15539979","settings":{"structure":"30","margin":{"unit":"px","top":"20","right":0,"bottom":"0","left":0,"isLinked":false}},"elements":[{"id":"72fdc037","settings":{"_column_size":33,"_inline_size":24.023},"elements":[],"isInner":true,"elType":"column"},{"id":"ff47a41","settings":{"_column_size":33,"_inline_size":52.05,"margin_mobile":{"unit":"px","top":"0","right":"10","bottom":"0","left":"10","isLinked":false}},"elements":[{"id":"2a561437","settings":{"shortcode":"[mc4wp_form id=\"122\"]"},"elements":[],"isInner":false,"widgetType":"shortcode","elType":"widget"}],"isInner":true,"elType":"column"},{"id":"5b3da203","settings":{"_column_size":33,"_inline_size":23.959},"elements":[],"isInner":true,"elType":"column"}],"isInner":true,"elType":"section"},{"id":"a784314","settings":{"space":{"unit":"px","size":58,"sizes":[]}},"elements":[],"isInner":false,"widgetType":"spacer","elType":"widget"}],"isInner":false,"elType":"column"}],"isInner":false,"elType":"section"}]}